[
  {
    "title": "A Magnificent Life - Sylvain Chomet",
    "showtime": "Friday, March 27, 3:00PM",
    "link": "https://am.ticketmaster.com/tiff/ism/Nk0yNzMwVDI=",
    "source": "TIFF Bell Lightbox"
  },
  {
    "title": "A Magnificent Life - Sylvain Chomet",
    "showtime": "Friday, March 27, 6:00PM",
    "link": "https://am.ticketmaster.com/tiff/ism/Nk0yNzYwVDI=",
    "source": "TIFF Bell Lightbox"
  },
  {
    "title": "Alpha - Julia Ducournau",
    "showtime": "Friday, March 27, 8:15PM",
    "link": "https://am.ticketmaster.com/tiff/ism/Nk0yNzgxVDI=",
    "source": "TIFF Bell Lightbox"
  },
  {
    "title": "Miroirs No. 3 - Christian Petzold",
    "showtime": "Friday, March 27, 1:00PM",
    "link": "https://am.ticketmaster.com/tiff/ism/Nk0yNzEwVDQ=",
    "source": "TIFF Bell Lightbox"
  },
  {
    "title": "Miroirs No. 3 - Christian Petzold",
    "showtime": "Friday, March 27, 3:30PM",
    "link": "https://am.ticketmaster.com/tiff/ism/Nk0yNzMzVDQ=",
    "source": "TIFF Bell Lightbox"
  },
  {
    "title": "Miroirs No. 3 - Christian Petzold",
    "showtime": "Friday, March 27, 8:40PM",
    "link": "https://am.ticketmaster.com/tiff/ism/Nk0yNzg0VDQ=",
    "source": "TIFF Bell Lightbox"
  },
  {
    "title": "Profils paysans: Le quotidien preceded by Quoi de neuf au Garet ?",
    "showtime": "Friday, March 27, 6:30PM",
    "link": "https://am.ticketmaster.com/tiff/ism/Nk0yNzYzVDQ=",
    "source": "TIFF Bell Lightbox"
  },
  {
    "title": "Silver Screenings: The Queen of My Dreams",
    "showtime": "Friday, March 27, 12:00PM",
    "link": "https://am.ticketmaster.com/tiff/ism/Nk0yN0wwVDE=",
    "source": "TIFF Bell Lightbox"
  },
  {
    "title": "Sirāt - Oliver Laxe",
    "showtime": "Friday, March 27, 4:00PM",
    "link": "https://am.ticketmaster.com/tiff/ism/Nk0yNzQwVDU=",
    "source": "TIFF Bell Lightbox"
  },
  {
    "title": "The AI Doc: Or How I Became an Apocaloptimist - Daniel Roher, Charlie Tyrell",
    "showtime": "Friday, March 27, 12:15PM",
    "link": "https://am.ticketmaster.com/tiff/ism/Nk0yN0wxVDI=",
    "source": "TIFF Bell Lightbox"
  },
  {
    "title": "The AI Doc: Or How I Became an Apocaloptimist - Daniel Roher, Charlie Tyrell",
    "showtime": "Friday, March 27, 3:45PM",
    "link": "https://am.ticketmaster.com/tiff/ism/Nk0yNzM0VDE=",
    "source": "TIFF Bell Lightbox"
  },
  {
    "title": "The AI Doc: Or How I Became an Apocaloptimist - Daniel Roher, Charlie Tyrell",
    "showtime": "Friday, March 27, 6:15PM",
    "link": "https://am.ticketmaster.com/tiff/ism/Nk0yNzYxVDE=",
    "source": "TIFF Bell Lightbox"
  },
  {
    "title": "The AI Doc: Or How I Became an Apocaloptimist - Daniel Roher, Charlie Tyrell",
    "showtime": "Friday, March 27, 10:00PM",
    "link": "https://am.ticketmaster.com/tiff/ism/Nk0yNzAwVDM=",
    "source": "TIFF Bell Lightbox"
  },
  {
    "title": "The Things You Kill - Alireza Khatami",
    "showtime": "Friday, March 27, 12:45PM",
    "link": "https://am.ticketmaster.com/tiff/ism/Nk0yN0w0VDM=",
    "source": "TIFF Bell Lightbox"
  },
  {
    "title": "The Things You Kill - Alireza Khatami",
    "showtime": "Friday, March 27, 6:45PM",
    "link": "https://am.ticketmaster.com/tiff/ism/Nk0yNzY0VDU=",
    "source": "TIFF Bell Lightbox"
  },
  {
    "title": "The Things You Kill - Alireza Khatami",
    "showtime": "Friday, March 27, 9:30PM",
    "link": "https://am.ticketmaster.com/tiff/ism/Nk0yNzkzVDU=",
    "source": "TIFF Bell Lightbox"
  },
  {
    "title": "Two Prosecutors - Sergei Loznitsa",
    "showtime": "Friday, March 27, 1:15PM",
    "link": "https://am.ticketmaster.com/tiff/ism/Nk0yNzExVDU=",
    "source": "TIFF Bell Lightbox"
  },
  {
    "title": "Two Prosecutors - Sergei Loznitsa",
    "showtime": "Friday, March 27, 8:45PM",
    "link": "https://am.ticketmaster.com/tiff/ism/Nk0yNzg0VDE=",
    "source": "TIFF Bell Lightbox"
  },
  {
    "title": "A Magnificent Life - Sylvain Chomet",
    "showtime": "Saturday, March 28, 8:30PM",
    "link": "https://am.ticketmaster.com/tiff/ism/Nk0yODgzVDE=",
    "source": "TIFF Bell Lightbox"
  },
  {
    "title": "Alpha - Julia Ducournau",
    "showtime": "Saturday, March 28, 3:00PM",
    "link": "https://am.ticketmaster.com/tiff/ism/Nk0yODMwVDE=",
    "source": "TIFF Bell Lightbox"
  },
  {
    "title": "Conversation Piece - Luchino Visconti",
    "showtime": "Saturday, March 28, 3:30PM",
    "link": "https://am.ticketmaster.com/tiff/ism/Nk0yODMzVDQ=",
    "source": "TIFF Bell Lightbox"
  },
  {
    "title": "La vie moderne - Raymond Depardon",
    "showtime": "Saturday, March 28, 6:30PM",
    "link": "https://am.ticketmaster.com/tiff/ism/Nk0yODYzVDQ=",
    "source": "TIFF Bell Lightbox"
  },
  {
    "title": "Miroirs No. 3 - Christian Petzold",
    "showtime": "Saturday, March 28, 1:15PM",
    "link": "https://am.ticketmaster.com/tiff/ism/Nk0yODExVDQ=",
    "source": "TIFF Bell Lightbox"
  },
  {
    "title": "Miroirs No. 3 - Christian Petzold",
    "showtime": "Saturday, March 28, 6:15PM",
    "link": "https://am.ticketmaster.com/tiff/ism/Nk0yODYxVDU=",
    "source": "TIFF Bell Lightbox"
  },
  {
    "title": "Sirāt - Oliver Laxe",
    "showtime": "Saturday, March 28, 12:30PM",
    "link": "https://am.ticketmaster.com/tiff/ism/Nk0yOEwzVDU=",
    "source": "TIFF Bell Lightbox"
  },
  {
    "title": "The AI Doc: Or How I Became an Apocaloptimist - Daniel Roher, Charlie Tyrell",
    "showtime": "Saturday, March 28, 12:00PM",
    "link": "https://am.ticketmaster.com/tiff/ism/Nk0yOEwwVDI=",
    "source": "TIFF Bell Lightbox"
  },
  {
    "title": "The AI Doc: Or How I Became an Apocaloptimist - Daniel Roher, Charlie Tyrell",
    "showtime": "Saturday, March 28, 2:45PM",
    "link": "https://am.ticketmaster.com/tiff/ism/Nk0yODI0VDI=",
    "source": "TIFF Bell Lightbox"
  },
  {
    "title": "The AI Doc: Or How I Became an Apocaloptimist - Daniel Roher, Charlie Tyrell",
    "showtime": "Saturday, March 28, 6:00PM",
    "link": "https://am.ticketmaster.com/tiff/ism/Nk0yODYwVDE=",
    "source": "TIFF Bell Lightbox"
  },
  {
    "title": "The AI Doc: Or How I Became an Apocaloptimist - Daniel Roher, Charlie Tyrell",
    "showtime": "Saturday, March 28, 8:45PM",
    "link": "https://am.ticketmaster.com/tiff/buy/ism/Nk0yODg0VDQ=",
    "source": "TIFF Bell Lightbox"
  },
  {
    "title": "The Things You Kill - Alireza Khatami",
    "showtime": "Saturday, March 28, 12:15PM",
    "link": "https://am.ticketmaster.com/tiff/ism/Nk0yOEwxVDE=",
    "source": "TIFF Bell Lightbox"
  },
  {
    "title": "The Things You Kill - Alireza Khatami",
    "showtime": "Saturday, March 28, 3:15PM",
    "link": "https://am.ticketmaster.com/tiff/ism/Nk0yODMxVDU=",
    "source": "TIFF Bell Lightbox"
  },
  {
    "title": "The Things You Kill - Alireza Khatami",
    "showtime": "Saturday, March 28, 8:25PM",
    "link": "https://am.ticketmaster.com/tiff/ism/Nk0yODgyVDU=",
    "source": "TIFF Bell Lightbox"
  },
  {
    "title": "Two Prosecutors - Sergei Loznitsa",
    "showtime": "Saturday, March 28, 7:00PM",
    "link": "https://am.ticketmaster.com/tiff/ism/Nk0yODcwVDI=",
    "source": "TIFF Bell Lightbox"
  },
  {
    "title": "A Magnificent Life - Sylvain Chomet",
    "showtime": "Sunday, March 29, 1:30PM",
    "link": "https://am.ticketmaster.com/tiff/ism/Nk0yOTEzVDI=",
    "source": "TIFF Bell Lightbox"
  },
  {
    "title": "Alpha - Julia Ducournau",
    "showtime": "Sunday, March 29, 6:45PM",
    "link": "https://am.ticketmaster.com/tiff/ism/Nk0yOTY0VDI=",
    "source": "TIFF Bell Lightbox"
  },
  {
    "title": "International Cinema Cafe",
    "showtime": "Sunday, March 29, 10:30AM",
    "link": "https://am.ticketmaster.com/tiff/buy/ism/Nk0yOUozVDE=",
    "source": "TIFF Bell Lightbox"
  },
  {
    "title": "Miroirs No. 3 - Christian Petzold",
    "showtime": "Sunday, March 29, 12:30PM",
    "link": "https://am.ticketmaster.com/tiff/ism/Nk0yOUwzVDU=",
    "source": "TIFF Bell Lightbox"
  },
  {
    "title": "Miroirs No. 3 - Christian Petzold",
    "showtime": "Sunday, March 29, 6:00PM",
    "link": "https://am.ticketmaster.com/tiff/ism/Nk0yOTYwVDU=",
    "source": "TIFF Bell Lightbox"
  },
  {
    "title": "Miroirs No. 3 - Christian Petzold",
    "showtime": "Sunday, March 29, 9:00PM",
    "link": "https://am.ticketmaster.com/tiff/ism/Nk0yOTkwVDQ=",
    "source": "TIFF Bell Lightbox"
  },
  {
    "title": "Paris preceded by New York, N.Y.",
    "showtime": "Sunday, March 29, 6:30PM",
    "link": "https://am.ticketmaster.com/tiff/ism/Nk0yOTYzVDQ=",
    "source": "TIFF Bell Lightbox"
  },
  {
    "title": "The AI Doc: Or How I Became an Apocaloptimist - Daniel Roher, Charlie Tyrell",
    "showtime": "Sunday, March 29, 2:00PM",
    "link": "https://am.ticketmaster.com/tiff/ism/Nk0yOTIwVDE=",
    "source": "TIFF Bell Lightbox"
  },
  {
    "title": "The AI Doc: Or How I Became an Apocaloptimist - Daniel Roher, Charlie Tyrell",
    "showtime": "Sunday, March 29, 4:30PM",
    "link": "https://am.ticketmaster.com/tiff/ism/Nk0yOTQzVDE=",
    "source": "TIFF Bell Lightbox"
  },
  {
    "title": "The AI Doc: Or How I Became an Apocaloptimist - Daniel Roher, Charlie Tyrell",
    "showtime": "Sunday, March 29, 7:00PM",
    "link": "https://am.ticketmaster.com/tiff/ism/Nk0yOTcwVDE=",
    "source": "TIFF Bell Lightbox"
  },
  {
    "title": "The AI Doc: Or How I Became an Apocaloptimist - Daniel Roher, Charlie Tyrell",
    "showtime": "Sunday, March 29, 9:30PM",
    "link": "https://am.ticketmaster.com/tiff/ism/Nk0yOTkzVDE=",
    "source": "TIFF Bell Lightbox"
  },
  {
    "title": "The Things You Kill - Alireza Khatami",
    "showtime": "Sunday, March 29, 1:00PM",
    "link": "https://am.ticketmaster.com/tiff/ism/Nk0yOTEwVDQ=",
    "source": "TIFF Bell Lightbox"
  },
  {
    "title": "The Things You Kill - Alireza Khatami",
    "showtime": "Sunday, March 29, 3:00PM",
    "link": "https://am.ticketmaster.com/tiff/ism/Nk0yOTMwVDU=",
    "source": "TIFF Bell Lightbox"
  },
  {
    "title": "The Things You Kill - Alireza Khatami",
    "showtime": "Sunday, March 29, 8:15PM",
    "link": "https://am.ticketmaster.com/tiff/ism/Nk0yOTgxVDU=",
    "source": "TIFF Bell Lightbox"
  },
  {
    "title": "Two Prosecutors - Sergei Loznitsa",
    "showtime": "Sunday, March 29, 3:45PM",
    "link": "https://am.ticketmaster.com/tiff/ism/Nk0yOTM0VDI=",
    "source": "TIFF Bell Lightbox"
  },
  {
    "title": "Wild Rose - Tom Harper",
    "showtime": "Sunday, March 29, 4:00PM",
    "link": "https://am.ticketmaster.com/tiff/ism/Nk0yOTQwVDQ=",
    "source": "TIFF Bell Lightbox"
  },
  {
    "title": "A Magnificent Life - Sylvain Chomet",
    "showtime": "Tuesday, March 31, 6:00PM",
    "link": "https://am.ticketmaster.com/tiff/ism/Nk0zMTYwVDI=",
    "source": "TIFF Bell Lightbox"
  },
  {
    "title": "Journal de France - Raymond Depardon, Claudine Nougaret",
    "showtime": "Tuesday, March 31, 6:30PM",
    "link": "https://am.ticketmaster.com/tiff/ism/Nk0zMTYzVDQ=",
    "source": "TIFF Bell Lightbox"
  },
  {
    "title": "Miroirs No. 3 - Christian Petzold",
    "showtime": "Tuesday, March 31, 6:25PM",
    "link": "https://am.ticketmaster.com/tiff/ism/Nk0zMTYyVDM=",
    "source": "TIFF Bell Lightbox"
  },
  {
    "title": "Sirāt - Oliver Laxe",
    "showtime": "Tuesday, March 31, 6:45PM",
    "link": "https://am.ticketmaster.com/tiff/ism/Nk0zMTY0VDU=",
    "source": "TIFF Bell Lightbox"
  },
  {
    "title": "The AI Doc: Or How I Became an Apocaloptimist - Daniel Roher, Charlie Tyrell",
    "showtime": "Tuesday, March 31, 6:15PM",
    "link": "https://am.ticketmaster.com/tiff/ism/Nk0zMTYxVDE=",
    "source": "TIFF Bell Lightbox"
  },
  {
    "title": "The Things You Kill - Alireza Khatami",
    "showtime": "Tuesday, March 31, 8:45PM",
    "link": "https://am.ticketmaster.com/tiff/ism/Nk0zMTg0VDM=",
    "source": "TIFF Bell Lightbox"
  },
  {
    "title": "Two Prosecutors - Sergei Loznitsa",
    "showtime": "Tuesday, March 31, 8:15PM",
    "link": "https://am.ticketmaster.com/tiff/ism/Nk0zMTgxVDI=",
    "source": "TIFF Bell Lightbox"
  },
  {
    "title": "A Magnificent Life - Sylvain Chomet",
    "showtime": "Wednesday, April 1, 4:45PM",
    "link": "https://am.ticketmaster.com/tiff/ism/NkEwMTQ0VDI=",
    "source": "TIFF Bell Lightbox"
  },
  {
    "title": "A Magnificent Life - Sylvain Chomet",
    "showtime": "Wednesday, April 1, 6:50PM",
    "link": "https://am.ticketmaster.com/tiff/ism/NkEwMTY1VDM=",
    "source": "TIFF Bell Lightbox"
  },
  {
    "title": "A New Love in Tokyo - Banmei Takahashi",
    "showtime": "Wednesday, April 1, 6:30PM",
    "link": "https://am.ticketmaster.com/tiff/ism/NkEwMTYzVDQ=",
    "source": "TIFF Bell Lightbox"
  },
  {
    "title": "Alpha - Julia Ducournau",
    "showtime": "Wednesday, April 1, 6:45PM",
    "link": "https://am.ticketmaster.com/tiff/ism/NkEwMTY0VDE=",
    "source": "TIFF Bell Lightbox"
  },
  {
    "title": "Miroirs No. 3 - Christian Petzold",
    "showtime": "Wednesday, April 1, 4:05PM",
    "link": "https://am.ticketmaster.com/tiff/ism/NkEwMTQwVDQ=",
    "source": "TIFF Bell Lightbox"
  },
  {
    "title": "Miroirs No. 3 - Christian Petzold",
    "showtime": "Wednesday, April 1, 9:15PM",
    "link": "https://am.ticketmaster.com/tiff/ism/NkEwMTkxVDM=",
    "source": "TIFF Bell Lightbox"
  },
  {
    "title": "The AI Doc: Or How I Became an Apocaloptimist - Daniel Roher, Charlie Tyrell",
    "showtime": "Wednesday, April 1, 4:15PM",
    "link": "https://am.ticketmaster.com/tiff/ism/NkEwMTQxVDE=",
    "source": "TIFF Bell Lightbox"
  },
  {
    "title": "The AI Doc: Or How I Became an Apocaloptimist - Daniel Roher, Charlie Tyrell",
    "showtime": "Wednesday, April 1, 7:00PM",
    "link": "https://am.ticketmaster.com/tiff/ism/NkEwMTcwVDI=",
    "source": "TIFF Bell Lightbox"
  },
  {
    "title": "The AI Doc: Or How I Became an Apocaloptimist - Daniel Roher, Charlie Tyrell",
    "showtime": "Wednesday, April 1, 9:45PM",
    "link": "https://am.ticketmaster.com/tiff/ism/NkEwMTk0VDE=",
    "source": "TIFF Bell Lightbox"
  },
  {
    "title": "The Things You Kill - Alireza Khatami",
    "showtime": "Wednesday, April 1, 4:30PM",
    "link": "https://am.ticketmaster.com/tiff/ism/NkEwMTQzVDU=",
    "source": "TIFF Bell Lightbox"
  },
  {
    "title": "The Things You Kill - Alireza Khatami",
    "showtime": "Wednesday, April 1, 7:15PM",
    "link": "https://am.ticketmaster.com/tiff/ism/NkEwMTcxVDU=",
    "source": "TIFF Bell Lightbox"
  },
  {
    "title": "The Things You Kill - Alireza Khatami",
    "showtime": "Wednesday, April 1, 9:30PM",
    "link": "https://am.ticketmaster.com/tiff/ism/NkEwMTkzVDI=",
    "source": "TIFF Bell Lightbox"
  },
  {
    "title": "Two Prosecutors - Sergei Loznitsa",
    "showtime": "Wednesday, April 1, 4:00PM",
    "link": "https://am.ticketmaster.com/tiff/ism/NkEwMTQwVDM=",
    "source": "TIFF Bell Lightbox"
  },
  {
    "title": "A Magnificent Life - Sylvain Chomet",
    "showtime": "Thursday, April 2, 8:30PM",
    "link": "https://am.ticketmaster.com/tiff/ism/NkEwMjgzVDI=",
    "source": "TIFF Bell Lightbox"
  },
  {
    "title": "Miroirs No. 3 - Christian Petzold",
    "showtime": "Thursday, April 2, 4:00PM",
    "link": "https://am.ticketmaster.com/tiff/ism/NkEwMjQwVDU=",
    "source": "TIFF Bell Lightbox"
  },
  {
    "title": "Miroirs No. 3 - Christian Petzold",
    "showtime": "Thursday, April 2, 6:40PM",
    "link": "https://am.ticketmaster.com/tiff/ism/NkEwMjY0VDU=",
    "source": "TIFF Bell Lightbox"
  },
  {
    "title": "Miroirs No. 3 - Christian Petzold",
    "showtime": "Thursday, April 2, 9:00PM",
    "link": "https://am.ticketmaster.com/tiff/ism/NkEwMjkwVDU=",
    "source": "TIFF Bell Lightbox"
  },
  {
    "title": "The AI Doc: Or How I Became an Apocaloptimist - Daniel Roher, Charlie Tyrell",
    "showtime": "Thursday, April 2, 4:15PM",
    "link": "https://am.ticketmaster.com/tiff/ism/NkEwMjQxVDE=",
    "source": "TIFF Bell Lightbox"
  },
  {
    "title": "The AI Doc: Or How I Became an Apocaloptimist - Daniel Roher, Charlie Tyrell",
    "showtime": "Thursday, April 2, 6:00PM",
    "link": "https://am.ticketmaster.com/tiff/ism/NkEwMjYwVDI=",
    "source": "TIFF Bell Lightbox"
  },
  {
    "title": "The AI Doc: Or How I Became an Apocaloptimist - Daniel Roher, Charlie Tyrell",
    "showtime": "Thursday, April 2, 9:30PM",
    "link": "https://am.ticketmaster.com/tiff/ism/NkEwMjkzVDE=",
    "source": "TIFF Bell Lightbox"
  },
  {
    "title": "The Things You Kill - Alireza Khatami",
    "showtime": "Thursday, April 2, 4:30PM",
    "link": "https://am.ticketmaster.com/tiff/ism/NkEwMjQzVDM=",
    "source": "TIFF Bell Lightbox"
  },
  {
    "title": "The Things You Kill - Alireza Khatami",
    "showtime": "Thursday, April 2, 7:30PM",
    "link": "https://am.ticketmaster.com/tiff/ism/NkEwMjczVDM=",
    "source": "TIFF Bell Lightbox"
  },
  {
    "title": "The Things You Kill - Alireza Khatami",
    "showtime": "Thursday, April 2, 9:45PM",
    "link": "https://am.ticketmaster.com/tiff/ism/NkEwMjk0VDQ=",
    "source": "TIFF Bell Lightbox"
  },
  {
    "title": "Two Prosecutors - Sergei Loznitsa",
    "showtime": "Thursday, April 2, 6:45PM",
    "link": "https://am.ticketmaster.com/tiff/ism/NkEwMjY0VDE=",
    "source": "TIFF Bell Lightbox"
  },
  {
    "title": "What Does That Nature Say to You - Hong Sangsoo",
    "showtime": "Thursday, April 2, 6:30PM",
    "link": "https://am.ticketmaster.com/tiff/ism/NkEwMjYzVDQ=",
    "source": "TIFF Bell Lightbox"
  },
  {
    "title": "Agatha's Almanac - Amalie Atkins",
    "showtime": "Friday, April 3, 7:00PM",
    "link": "https://am.ticketmaster.com/tiff/ism/NkEwMzcwVDI=",
    "source": "TIFF Bell Lightbox"
  },
  {
    "title": "Marc by Sofia - Sofia Coppola",
    "showtime": "Friday, April 3, 1:30PM",
    "link": "https://am.ticketmaster.com/tiff/ism/NkEwMzEzVDI=",
    "source": "TIFF Bell Lightbox"
  },
  {
    "title": "Marc by Sofia - Sofia Coppola",
    "showtime": "Friday, April 3, 3:45PM",
    "link": "https://am.ticketmaster.com/tiff/ism/NkEwMzM0VDI=",
    "source": "TIFF Bell Lightbox"
  },
  {
    "title": "Marc by Sofia - Sofia Coppola",
    "showtime": "Friday, April 3, 6:15PM",
    "link": "https://am.ticketmaster.com/tiff/ism/NkEwMzYxVDE=",
    "source": "TIFF Bell Lightbox"
  },
  {
    "title": "Marc by Sofia - Sofia Coppola",
    "showtime": "Friday, April 3, 9:30PM",
    "link": "https://am.ticketmaster.com/tiff/ism/NkEwMzkzVDM=",
    "source": "TIFF Bell Lightbox"
  },
  {
    "title": "Palestine '36 - Annemarie Jacir",
    "showtime": "Friday, April 3, 12:45PM",
    "link": "https://am.ticketmaster.com/tiff/ism/NkEwM0w0VDE=",
    "source": "TIFF Bell Lightbox"
  },
  {
    "title": "Palestine '36 - Annemarie Jacir",
    "showtime": "Friday, April 3, 3:30PM",
    "link": "https://am.ticketmaster.com/tiff/ism/NkEwMzMzVDE=",
    "source": "TIFF Bell Lightbox"
  },
  {
    "title": "Palestine '36 - Annemarie Jacir",
    "showtime": "Friday, April 3, 8:30PM",
    "link": "https://am.ticketmaster.com/tiff/ism/NkEwMzgzVDE=",
    "source": "TIFF Bell Lightbox"
  },
  {
    "title": "The Blue Trail - Gabriel Mascaro",
    "showtime": "Friday, April 3, 6:45PM",
    "link": "https://am.ticketmaster.com/tiff/ism/NkEwMzY0VDQ=",
    "source": "TIFF Bell Lightbox"
  },
  {
    "title": "The Long Day Closes preceded by Passing Time",
    "showtime": "Friday, April 3, 6:30PM",
    "link": "https://am.ticketmaster.com/tiff/ism/NkEwMzYzVDM=",
    "source": "TIFF Bell Lightbox"
  },
  {
    "title": "Agatha's Almanac - Amalie Atkins",
    "showtime": "Saturday, April 4, 7:30PM",
    "link": "https://am.ticketmaster.com/tiff/ism/NkEwNDczVDM=",
    "source": "TIFF Bell Lightbox"
  },
  {
    "title": "Marc by Sofia - Sofia Coppola",
    "showtime": "Saturday, April 4, 12:00PM",
    "link": "https://am.ticketmaster.com/tiff/ism/NkEwNEwwVDI=",
    "source": "TIFF Bell Lightbox"
  },
  {
    "title": "Marc by Sofia - Sofia Coppola",
    "showtime": "Saturday, April 4, 3:45PM",
    "link": "https://am.ticketmaster.com/tiff/ism/NkEwNDM0VDE=",
    "source": "TIFF Bell Lightbox"
  },
  {
    "title": "Marc by Sofia - Sofia Coppola",
    "showtime": "Saturday, April 4, 7:00PM",
    "link": "https://am.ticketmaster.com/tiff/ism/NkEwNDcwVDI=",
    "source": "TIFF Bell Lightbox"
  },
  {
    "title": "Marc by Sofia - Sofia Coppola",
    "showtime": "Saturday, April 4, 9:45PM",
    "link": "https://am.ticketmaster.com/tiff/ism/NkEwNDk0VDM=",
    "source": "TIFF Bell Lightbox"
  },
  {
    "title": "Palestine '36 - Annemarie Jacir",
    "showtime": "Saturday, April 4, 1:00PM",
    "link": "https://am.ticketmaster.com/tiff/ism/NkEwNDEwVDE=",
    "source": "TIFF Bell Lightbox"
  },
  {
    "title": "Palestine '36 - Annemarie Jacir",
    "showtime": "Saturday, April 4, 7:15PM",
    "link": "https://am.ticketmaster.com/tiff/ism/NkEwNDcxVDE=",
    "source": "TIFF Bell Lightbox"
  },
  {
    "title": "Palestine '36 - Annemarie Jacir",
    "showtime": "Saturday, April 4, 9:30PM",
    "link": "https://am.ticketmaster.com/tiff/ism/NkEwNDkzVDI=",
    "source": "TIFF Bell Lightbox"
  },
  {
    "title": "Stuck - Stuart Gordon",
    "showtime": "Saturday, April 4, 6:30PM",
    "link": "https://am.ticketmaster.com/tiff/ism/NkEwNDYzVDQ=",
    "source": "TIFF Bell Lightbox"
  },
  {
    "title": "The Blue Trail - Gabriel Mascaro",
    "showtime": "Saturday, April 4, 2:15PM",
    "link": "https://am.ticketmaster.com/tiff/ism/NkEwNDIxVDI=",
    "source": "TIFF Bell Lightbox"
  },
  {
    "title": "Agatha's Almanac - Amalie Atkins",
    "showtime": "Sunday, April 5, 1:45PM",
    "link": "https://am.ticketmaster.com/tiff/ism/NkEwNTE0VDM=",
    "source": "TIFF Bell Lightbox"
  },
  {
    "title": "Benediction preceded by But Why?",
    "showtime": "Sunday, April 5, 6:30PM",
    "link": "https://am.ticketmaster.com/tiff/ism/NkEwNTYzVDM=",
    "source": "TIFF Bell Lightbox"
  },
  {
    "title": "Marc by Sofia - Sofia Coppola",
    "showtime": "Sunday, April 5, 1:15PM",
    "link": "https://am.ticketmaster.com/tiff/ism/NkEwNTExVDE=",
    "source": "TIFF Bell Lightbox"
  },
  {
    "title": "Marc by Sofia - Sofia Coppola",
    "showtime": "Sunday, April 5, 3:45PM",
    "link": "https://am.ticketmaster.com/tiff/ism/NkEwNTM0VDI=",
    "source": "TIFF Bell Lightbox"
  },
  {
    "title": "Marc by Sofia - Sofia Coppola",
    "showtime": "Sunday, April 5, 6:00PM",
    "link": "https://am.ticketmaster.com/tiff/ism/NkEwNTYwVDI=",
    "source": "TIFF Bell Lightbox"
  },
  {
    "title": "Marc by Sofia - Sofia Coppola",
    "showtime": "Sunday, April 5, 9:30PM",
    "link": "https://am.ticketmaster.com/tiff/ism/NkEwNTkzVDM=",
    "source": "TIFF Bell Lightbox"
  },
  {
    "title": "Palestine '36 - Annemarie Jacir",
    "showtime": "Sunday, April 5, 12:30PM",
    "link": "https://am.ticketmaster.com/tiff/ism/NkEwNUwzVDI=",
    "source": "TIFF Bell Lightbox"
  },
  {
    "title": "Palestine '36 - Annemarie Jacir",
    "showtime": "Sunday, April 5, 3:30PM",
    "link": "https://am.ticketmaster.com/tiff/ism/NkEwNTMzVDE=",
    "source": "TIFF Bell Lightbox"
  },
  {
    "title": "Palestine '36 - Annemarie Jacir",
    "showtime": "Sunday, April 5, 7:00PM",
    "link": "https://am.ticketmaster.com/tiff/ism/NkEwNTcwVDE=",
    "source": "TIFF Bell Lightbox"
  },
  {
    "title": "Singin' in the Rain - Stanley Donen, Gene Kelly",
    "showtime": "Sunday, April 5, 4:00PM",
    "link": "https://am.ticketmaster.com/tiff/ism/NkEwNTQwVDM=",
    "source": "TIFF Bell Lightbox"
  },
  {
    "title": "The Blue Trail - Gabriel Mascaro",
    "showtime": "Sunday, April 5, 8:15PM",
    "link": "https://am.ticketmaster.com/tiff/ism/NkEwNTgxVDI=",
    "source": "TIFF Bell Lightbox"
  },
  {
    "title": "Marc by Sofia - Sofia Coppola",
    "showtime": "Tuesday, April 7, 6:15PM",
    "link": "https://am.ticketmaster.com/tiff/ism/NkEwNzYxVDI=",
    "source": "TIFF Bell Lightbox"
  },
  {
    "title": "Palestine '36 - Annemarie Jacir",
    "showtime": "Tuesday, April 7, 8:15PM",
    "link": "https://am.ticketmaster.com/tiff/ism/NkEwNzgxVDE=",
    "source": "TIFF Bell Lightbox"
  },
  {
    "title": "The Blue Trail - Gabriel Mascaro",
    "showtime": "Tuesday, April 7, 6:00PM",
    "link": "https://am.ticketmaster.com/tiff/ism/NkEwNzYwVDE=",
    "source": "TIFF Bell Lightbox"
  },
  {
    "title": "The Neon Bible with recorded intro by Jacob Tierney",
    "showtime": "Tuesday, April 7, 6:30PM",
    "link": "https://am.ticketmaster.com/tiff/ism/NkEwNzYzVDM=",
    "source": "TIFF Bell Lightbox"
  },
  {
    "title": "Light Noise Smoke: The Films of Tomonari Nishikawa",
    "showtime": "Wednesday, April 8, 7:00PM",
    "link": "https://am.ticketmaster.com/tiff/ism/NkEwODcwVDQ=",
    "source": "TIFF Bell Lightbox"
  },
  {
    "title": "Marc by Sofia - Sofia Coppola",
    "showtime": "Wednesday, April 8, 4:15PM",
    "link": "https://am.ticketmaster.com/tiff/ism/NkEwODQxVDM=",
    "source": "TIFF Bell Lightbox"
  },
  {
    "title": "Marc by Sofia - Sofia Coppola",
    "showtime": "Wednesday, April 8, 6:30PM",
    "link": "https://am.ticketmaster.com/tiff/ism/NkEwODYzVDM=",
    "source": "TIFF Bell Lightbox"
  },
  {
    "title": "Palestine '36 - Annemarie Jacir",
    "showtime": "Wednesday, April 8, 4:00PM",
    "link": "https://am.ticketmaster.com/tiff/ism/NkEwODQwVDE=",
    "source": "TIFF Bell Lightbox"
  },
  {
    "title": "Palestine '36 - Annemarie Jacir",
    "showtime": "Wednesday, April 8, 6:45PM",
    "link": "https://am.ticketmaster.com/tiff/ism/NkEwODY0VDE=",
    "source": "TIFF Bell Lightbox"
  },
  {
    "title": "The Blue Trail - Gabriel Mascaro",
    "showtime": "Wednesday, April 8, 3:45PM",
    "link": "https://am.ticketmaster.com/tiff/ism/NkEwODM0VDQ=",
    "source": "TIFF Bell Lightbox"
  },
  {
    "title": "The Blue Trail - Gabriel Mascaro",
    "showtime": "Wednesday, April 8, 8:45PM",
    "link": "https://am.ticketmaster.com/tiff/ism/NkEwODg0VDM=",
    "source": "TIFF Bell Lightbox"
  },
  {
    "title": "100 Sunset - Kunsang Kyirong",
    "showtime": "Thursday, April 9, 6:30PM",
    "link": "https://am.ticketmaster.com/tiff/ism/NkEwOTYzVDM=",
    "source": "TIFF Bell Lightbox"
  },
  {
    "title": "Agatha's Almanac - Amalie Atkins",
    "showtime": "Thursday, April 9, 6:20PM",
    "link": "https://am.ticketmaster.com/tiff/ism/NkEwOTYyVDI=",
    "source": "TIFF Bell Lightbox"
  },
  {
    "title": "Marc by Sofia - Sofia Coppola",
    "showtime": "Thursday, April 9, 4:10PM",
    "link": "https://am.ticketmaster.com/tiff/ism/NkEwOTQxVDM=",
    "source": "TIFF Bell Lightbox"
  },
  {
    "title": "Marc by Sofia - Sofia Coppola",
    "showtime": "Thursday, April 9, 7:00PM",
    "link": "https://am.ticketmaster.com/tiff/ism/NkEwOTcwVDE=",
    "source": "TIFF Bell Lightbox"
  },
  {
    "title": "Palestine '36 - Annemarie Jacir",
    "showtime": "Thursday, April 9, 4:15PM",
    "link": "https://am.ticketmaster.com/tiff/ism/NkEwOTQxVDE=",
    "source": "TIFF Bell Lightbox"
  },
  {
    "title": "Palestine '36 - Annemarie Jacir",
    "showtime": "Thursday, April 9, 8:30PM",
    "link": "https://am.ticketmaster.com/tiff/ism/NkEwOTgzVDI=",
    "source": "TIFF Bell Lightbox"
  },
  {
    "title": "The Blue Trail - Gabriel Mascaro",
    "showtime": "Thursday, April 9, 4:00PM",
    "link": "https://am.ticketmaster.com/tiff/ism/NkEwOTQwVDI=",
    "source": "TIFF Bell Lightbox"
  },
  {
    "title": "The House of Mirth - Terence Davies",
    "showtime": "Friday, April 10, 6:30PM",
    "link": "https://am.ticketmaster.com/tiff/ism/NkExMDYzVDM=",
    "source": "TIFF Bell Lightbox"
  },
  {
    "title": "A Quiet Passion - Terence Davies",
    "showtime": "Saturday, April 11, 5:30PM",
    "link": "https://am.ticketmaster.com/tiff/ism/NkExMTUzVDQ=",
    "source": "TIFF Bell Lightbox"
  },
  {
    "title": "Distant Voices, Still Lives preceded by Boogie",
    "showtime": "Saturday, April 11, 3:00PM",
    "link": "https://am.ticketmaster.com/tiff/ism/NkExMTMwVDQ=",
    "source": "TIFF Bell Lightbox"
  },
  {
    "title": "The Terence Davies Trilogy",
    "showtime": "Saturday, April 11, 12:00PM",
    "link": "https://am.ticketmaster.com/tiff/ism/NkExMUwwVDQ=",
    "source": "TIFF Bell Lightbox"
  },
  {
    "title": "Silver Screenings: Little Miss Sunshine with TIFF Next Wave",
    "showtime": "Sunday, April 12, 12:00PM",
    "link": "https://am.ticketmaster.com/tiff/ism/NkExMkwwVDE=",
    "source": "TIFF Bell Lightbox"
  },
  {
    "title": "Sunset Song - Terence Davies",
    "showtime": "Sunday, April 12, 7:30PM",
    "link": "https://am.ticketmaster.com/tiff/ism/NkExMjczVDI=",
    "source": "TIFF Bell Lightbox"
  },
  {
    "title": "The Deep Blue Sea - Terence Davies",
    "showtime": "Sunday, April 12, 5:00PM",
    "link": "https://am.ticketmaster.com/tiff/ism/NkExMjUwVDI=",
    "source": "TIFF Bell Lightbox"
  },
  {
    "title": "Secret Movie Club",
    "showtime": "Tuesday, April 14, 7:00PM",
    "link": "https://am.ticketmaster.com/tiff/buy/ism/NkExNDcwVDE=",
    "source": "TIFF Bell Lightbox"
  },
  {
    "title": "The Devil, Probably, with Cameron Bailey",
    "showtime": "Tuesday, April 14, 6:30PM",
    "link": "https://am.ticketmaster.com/tiff/ism/NkExNDYzVDM=",
    "source": "TIFF Bell Lightbox"
  },
  {
    "title": "Barbaracadabra with Barbara Ulrich and Renaud Lessard",
    "showtime": "Wednesday, April 15, 6:00PM",
    "link": "https://am.ticketmaster.com/tiff/ism/NkExNTYwVDM=",
    "source": "TIFF Bell Lightbox"
  },
  {
    "title": "In Conversation With... Salman Rushdie",
    "showtime": "Wednesday, April 15, 6:30PM",
    "link": "https://am.ticketmaster.com/tiff/ism/NkExNTYzVDE=",
    "source": "TIFF Bell Lightbox"
  },
  {
    "title": "Advance Screening: Roommates",
    "showtime": "Thursday, April 16, 6:15PM",
    "link": "https://am.ticketmaster.com/tiff/ism/NkExNjYxVDI=",
    "source": "TIFF Bell Lightbox"
  },
  {
    "title": "Benediction preceded by But Why?",
    "showtime": "Thursday, April 16, 6:30PM",
    "link": "https://am.ticketmaster.com/tiff/ism/NkExNjYzVDQ=",
    "source": "TIFF Bell Lightbox"
  },
  {
    "title": "Our Hero, Balthazar - Oscar Boyson",
    "showtime": "Thursday, April 16, 8:30PM",
    "link": "https://am.ticketmaster.com/tiff/ism/NkExNjgzVDM=",
    "source": "TIFF Bell Lightbox"
  },
  {
    "title": "Battle of the Scores + Opening Night Party",
    "showtime": "Friday, April 17, 7:00PM",
    "link": "https://am.ticketmaster.com/tiff/ism/NkExNzcwVDI=",
    "source": "TIFF Bell Lightbox"
  },
  {
    "title": "Burn - Makoto Nagahisa",
    "showtime": "Friday, April 17, 9:30PM",
    "link": "https://am.ticketmaster.com/tiff/ism/NkExNzkzVDM=",
    "source": "TIFF Bell Lightbox"
  },
  {
    "title": "Big Girls Don't Cry - Paloma Schneideman",
    "showtime": "Saturday, April 18, 5:30PM",
    "link": "https://am.ticketmaster.com/tiff/ism/NkExODUzVDM=",
    "source": "TIFF Bell Lightbox"
  },
  {
    "title": "Creators on a Wave: Alumni Spotlight",
    "showtime": "Saturday, April 18, 2:30PM",
    "link": "https://am.ticketmaster.com/tiff/ism/NkExODIzVDI=",
    "source": "TIFF Bell Lightbox"
  },
  {
    "title": "Drop-In: Camera Obscurities",
    "showtime": "Saturday, April 18, 1:00PM (Free)",
    "link": "https://tiff.net/events/drop-in-camera-obscurities",
    "source": "TIFF Bell Lightbox"
  },
  {
    "title": "High School Musical 3: Senior Year with Miss Moço",
    "showtime": "Saturday, April 18, 8:30PM",
    "link": "https://am.ticketmaster.com/tiff/ism/NkExODgzVDI=",
    "source": "TIFF Bell Lightbox"
  },
  {
    "title": "Isle Child - Thomas Percy Kim",
    "showtime": "Saturday, April 18, 8:45PM",
    "link": "https://am.ticketmaster.com/tiff/ism/NkExODg0VDM=",
    "source": "TIFF Bell Lightbox"
  },
  {
    "title": "Niñxs - Kani Lapuerta",
    "showtime": "Saturday, April 18, 5:00PM",
    "link": "https://am.ticketmaster.com/tiff/ism/NkExODUwVDQ=",
    "source": "TIFF Bell Lightbox"
  },
  {
    "title": "Thanks for Nothing - Stella Marie Markert",
    "showtime": "Saturday, April 18, 1:30PM",
    "link": "https://am.ticketmaster.com/tiff/ism/NkExODEzVDM=",
    "source": "TIFF Bell Lightbox"
  },
  {
    "title": "Young Creators Co-Lab: Aesthetic Overload: Finding Your Visual Style",
    "showtime": "Saturday, April 18, 11:00AM",
    "link": "https://am.ticketmaster.com/tiff/",
    "source": "TIFF Bell Lightbox"
  },
  {
    "title": "CAMP - Avalon Fast",
    "showtime": "Sunday, April 19, 4:05PM",
    "link": "https://am.ticketmaster.com/tiff/ism/NkExOTQwVDM=",
    "source": "TIFF Bell Lightbox"
  },
  {
    "title": "Drop-In: Young Creators Launch Pad",
    "showtime": "Sunday, April 19, 3:00PM (Free)",
    "link": "https://tiff.net/events/drop-in-young-creators-launch-pad",
    "source": "TIFF Bell Lightbox"
  },
  {
    "title": "If I Go Will They Miss Me - Walter Thompson-Hernández",
    "showtime": "Sunday, April 19, 1:45PM",
    "link": "https://am.ticketmaster.com/tiff/ism/NkExOTE0VDQ=",
    "source": "TIFF Bell Lightbox"
  },
  {
    "title": "Ish - Imran Paretta",
    "showtime": "Sunday, April 19, 7:15PM",
    "link": "https://am.ticketmaster.com/tiff/ism/NkExOTcxVDM=",
    "source": "TIFF Bell Lightbox"
  },
  {
    "title": "Young Creators Co-Lab: Costume in Conversation",
    "showtime": "Sunday, April 19, 11:00AM",
    "link": "https://am.ticketmaster.com/tiff/",
    "source": "TIFF Bell Lightbox"
  },
  {
    "title": "Young Creators Co-Lab: Music in Motion",
    "showtime": "Sunday, April 19, 1:30PM",
    "link": "https://am.ticketmaster.com/tiff/ism/NkExOTEzVDM=",
    "source": "TIFF Bell Lightbox"
  },
  {
    "title": "Young Creators Showcase",
    "showtime": "Sunday, April 19, 7:30PM",
    "link": "https://am.ticketmaster.com/tiff/ism/NkExOTczVDE=",
    "source": "TIFF Bell Lightbox"
  },
  {
    "title": "Of Time and the City - Terence Davies",
    "showtime": "Tuesday, April 21, 6:30PM",
    "link": "https://am.ticketmaster.com/tiff/ism/NkEyMTYzVDQ=",
    "source": "TIFF Bell Lightbox"
  },
  {
    "title": "A Silent Voice - Naoko Yamada",
    "showtime": "Wednesday, April 22, 6:30PM",
    "link": "https://am.ticketmaster.com/tiff/ism/NkEyMjYzVDM=",
    "source": "TIFF Bell Lightbox"
  },
  {
    "title": "Secret Movie Club",
    "showtime": "Tuesday, May 5, 7:00PM",
    "link": "https://am.ticketmaster.com/tiff/buy/ism/NlkwNTcwVDE=",
    "source": "TIFF Bell Lightbox"
  }
]