[
  {
    "title": "2026 Oscar-Nominated Short Films: Animated",
    "showtime": "Thursday, February 26, 6:35PM",
    "link": "https://am.ticketmaster.com/tiff/buy/ism/NkYyNjYzVDM=",
    "source": "TIFF Bell Lightbox"
  },
  {
    "title": "2026 Oscar-Nominated Short Films: Documentary",
    "showtime": "Thursday, February 26, 8:45PM",
    "link": "https://am.ticketmaster.com/tiff/buy/ism/NkYyNjg0VDM=",
    "source": "TIFF Bell Lightbox"
  },
  {
    "title": "2026 Oscar-Nominated Short Films: Live Action",
    "showtime": "Thursday, February 26",
    "link": "https://tiff.net/events/2026-oscar-nominated-short-films-live-action",
    "source": "TIFF Bell Lightbox"
  },
  {
    "title": "All That's Left of You - Cherien Dabis",
    "showtime": "Thursday, February 26, 7:45PM",
    "link": "https://am.ticketmaster.com/tiff/ism/NkYyNjc0VDU=",
    "source": "TIFF Bell Lightbox"
  },
  {
    "title": "Celebrating John Candy: The Exhibit",
    "showtime": "Thursday, February 26",
    "link": "https://tiff.net/events/celebrating-john-candy-the-exhibit",
    "source": "TIFF Bell Lightbox"
  },
  {
    "title": "Film Reference Library Public Hours",
    "showtime": "Thursday, February 26",
    "link": "https://tiff.net/events/film-reference-library-public-hours",
    "source": "TIFF Bell Lightbox"
  },
  {
    "title": "Magellan - Lav Diaz",
    "showtime": "Thursday, February 26",
    "link": "https://tiff.net/events/magellan",
    "source": "TIFF Bell Lightbox"
  },
  {
    "title": "Montreal, My Beautiful - Xiaodan He",
    "showtime": "Thursday, February 26",
    "link": "https://tiff.net/events/montreal-my-beautiful",
    "source": "TIFF Bell Lightbox"
  },
  {
    "title": "Sirāt - Oliver Laxe",
    "showtime": "Thursday, February 26, 9:45PM",
    "link": "https://am.ticketmaster.com/tiff/ism/NkYyNjk0VDQ=",
    "source": "TIFF Bell Lightbox"
  },
  {
    "title": "The Misconceived with James N. Kienitz Wilkins",
    "showtime": "Thursday, February 26, 6:30PM",
    "link": "https://am.ticketmaster.com/tiff/ism/NkYyNjYzVDQ=",
    "source": "TIFF Bell Lightbox"
  },
  {
    "title": "The Secret Agent - Kleber Mendonça Filho",
    "showtime": "Thursday, February 26, 7:15PM",
    "link": "https://am.ticketmaster.com/tiff/ism/NkYyNjcxVDE=",
    "source": "TIFF Bell Lightbox"
  },
  {
    "title": "2026 Oscar-Nominated Short Films: Animated",
    "showtime": "Friday, February 27, 2:15PM",
    "link": "https://am.ticketmaster.com/tiff/ism/NkYyNzIxVDE=",
    "source": "TIFF Bell Lightbox"
  },
  {
    "title": "2026 Oscar-Nominated Short Films: Animated",
    "showtime": "Friday, February 27, 4:30PM",
    "link": "https://am.ticketmaster.com/tiff/ism/NkYyNzQzVDI=",
    "source": "TIFF Bell Lightbox"
  },
  {
    "title": "2026 Oscar-Nominated Short Films: Documentary",
    "showtime": "Friday, February 27, 12:30PM",
    "link": "https://am.ticketmaster.com/tiff/ism/NkYyN0wzVDI=",
    "source": "TIFF Bell Lightbox"
  },
  {
    "title": "2026 Oscar-Nominated Short Films: Documentary",
    "showtime": "Friday, February 27, 7:45PM",
    "link": "https://am.ticketmaster.com/tiff/ism/NkYyNzc0VDE=",
    "source": "TIFF Bell Lightbox"
  },
  {
    "title": "2026 Oscar-Nominated Short Films: Live Action",
    "showtime": "Friday, February 27, 4:45PM",
    "link": "https://am.ticketmaster.com/tiff/ism/NkYyNzQ0VDE=",
    "source": "TIFF Bell Lightbox"
  },
  {
    "title": "2026 Oscar-Nominated Short Films: Live Action",
    "showtime": "Friday, February 27, 9:15PM",
    "link": "https://am.ticketmaster.com/tiff/ism/NkYyNzkxVDM=",
    "source": "TIFF Bell Lightbox"
  },
  {
    "title": "All That's Left of You - Cherien Dabis",
    "showtime": "Friday, February 27, 2:45PM",
    "link": "https://am.ticketmaster.com/tiff/ism/NkYyNzI0VDU=",
    "source": "TIFF Bell Lightbox"
  },
  {
    "title": "All That's Left of You - Cherien Dabis",
    "showtime": "Friday, February 27, 8:50PM",
    "link": "https://am.ticketmaster.com/tiff/ism/NkYyNzg1VDU=",
    "source": "TIFF Bell Lightbox"
  },
  {
    "title": "Celebrating John Candy: The Exhibit",
    "showtime": "Friday, February 27, 12:00PM (Free)",
    "link": "https://tiff.net/events/celebrating-john-candy-the-exhibit",
    "source": "TIFF Bell Lightbox"
  },
  {
    "title": "Days and Nights in the Forest - Satyajit Ray",
    "showtime": "Friday, February 27, 6:30PM",
    "link": "https://am.ticketmaster.com/tiff/ism/NkYyNzYzVDM=",
    "source": "TIFF Bell Lightbox"
  },
  {
    "title": "Film Reference Library Public Hours",
    "showtime": "Friday, February 27, 12:00PM",
    "link": "https://am.ticketmaster.com/tiff/",
    "source": "TIFF Bell Lightbox"
  },
  {
    "title": "Jimpa - Sophie Hyde",
    "showtime": "Friday, February 27, 12:45PM",
    "link": "https://am.ticketmaster.com/tiff/ism/NkYyN0w0VDM=",
    "source": "TIFF Bell Lightbox"
  },
  {
    "title": "Jimpa - Sophie Hyde",
    "showtime": "Friday, February 27, 6:45PM",
    "link": "https://am.ticketmaster.com/tiff/ism/NkYyNzY0VDI=",
    "source": "TIFF Bell Lightbox"
  },
  {
    "title": "Montreal, My Beautiful - Xiaodan He",
    "showtime": "Friday, February 27, 12:00PM",
    "link": "https://am.ticketmaster.com/tiff/ism/NkYyN0wwVDU=",
    "source": "TIFF Bell Lightbox"
  },
  {
    "title": "Montreal, My Beautiful - Xiaodan He",
    "showtime": "Friday, February 27, 6:00PM",
    "link": "https://am.ticketmaster.com/tiff/ism/NkYyNzYwVDU=",
    "source": "TIFF Bell Lightbox"
  },
  {
    "title": "Montreal, My Beautiful - Xiaodan He",
    "showtime": "Friday, February 27, 9:30PM",
    "link": "https://am.ticketmaster.com/tiff/ism/NkYyNzkzVDI=",
    "source": "TIFF Bell Lightbox"
  },
  {
    "title": "Pillion - Harry Lighton",
    "showtime": "Friday, February 27, 8:45PM",
    "link": "https://am.ticketmaster.com/tiff/ism/NkYyNzg0VDQ=",
    "source": "TIFF Bell Lightbox"
  },
  {
    "title": "Sirāt - Oliver Laxe",
    "showtime": "Friday, February 27, 12:15PM",
    "link": "https://am.ticketmaster.com/tiff/ism/NkYyN0wxVDQ=",
    "source": "TIFF Bell Lightbox"
  },
  {
    "title": "Sirāt - Oliver Laxe",
    "showtime": "Friday, February 27, 3:00PM",
    "link": "https://am.ticketmaster.com/tiff/ism/NkYyNzMwVDQ=",
    "source": "TIFF Bell Lightbox"
  },
  {
    "title": "The President's Cake - Hasan Hadi",
    "showtime": "Friday, February 27, 3:45PM",
    "link": "https://am.ticketmaster.com/tiff/ism/NkYyNzM0VDM=",
    "source": "TIFF Bell Lightbox"
  },
  {
    "title": "The President's Cake - Hasan Hadi",
    "showtime": "Friday, February 27, 6:15PM",
    "link": "https://am.ticketmaster.com/tiff/ism/NkYyNzYxVDQ=",
    "source": "TIFF Bell Lightbox"
  },
  {
    "title": "2026 Oscar-Nominated Short Films: Animated",
    "showtime": "Saturday, February 28, 1:00PM",
    "link": "https://am.ticketmaster.com/tiff/ism/NkYyODEwVDI=",
    "source": "TIFF Bell Lightbox"
  },
  {
    "title": "2026 Oscar-Nominated Short Films: Animated",
    "showtime": "Saturday, February 28, 4:15PM",
    "link": "https://am.ticketmaster.com/tiff/ism/NkYyODQxVDE=",
    "source": "TIFF Bell Lightbox"
  },
  {
    "title": "2026 Oscar-Nominated Short Films: Animated",
    "showtime": "Saturday, February 28, 9:35PM",
    "link": "https://am.ticketmaster.com/tiff/ism/NkYyODkzVDE=",
    "source": "TIFF Bell Lightbox"
  },
  {
    "title": "2026 Oscar-Nominated Short Films: Documentary",
    "showtime": "Saturday, February 28, 12:30PM",
    "link": "https://am.ticketmaster.com/tiff/ism/NkYyOEwzVDE=",
    "source": "TIFF Bell Lightbox"
  },
  {
    "title": "2026 Oscar-Nominated Short Films: Documentary",
    "showtime": "Saturday, February 28, 8:30PM",
    "link": "https://am.ticketmaster.com/tiff/ism/NkYyODgzVDM=",
    "source": "TIFF Bell Lightbox"
  },
  {
    "title": "2026 Oscar-Nominated Short Films: Live Action",
    "showtime": "Saturday, February 28, 3:15PM",
    "link": "https://am.ticketmaster.com/tiff/ism/NkYyODMxVDM=",
    "source": "TIFF Bell Lightbox"
  },
  {
    "title": "2026 Oscar-Nominated Short Films: Live Action",
    "showtime": "Saturday, February 28, 6:40PM",
    "link": "https://am.ticketmaster.com/tiff/ism/NkYyODY0VDE=",
    "source": "TIFF Bell Lightbox"
  },
  {
    "title": "All That's Left of You - Cherien Dabis",
    "showtime": "Saturday, February 28, 3:00PM",
    "link": "https://am.ticketmaster.com/tiff/ism/NkYyODMwVDU=",
    "source": "TIFF Bell Lightbox"
  },
  {
    "title": "Celebrating John Candy: The Exhibit",
    "showtime": "Saturday, February 28, 12:00PM (Free)",
    "link": "https://tiff.net/events/celebrating-john-candy-the-exhibit",
    "source": "TIFF Bell Lightbox"
  },
  {
    "title": "Days and Nights in the Forest - Satyajit Ray",
    "showtime": "Saturday, February 28, 4:00PM",
    "link": "https://am.ticketmaster.com/tiff/ism/NkYyODQwVDQ=",
    "source": "TIFF Bell Lightbox"
  },
  {
    "title": "Film Reference Library Public Hours",
    "showtime": "Saturday, February 28, 12:00PM",
    "link": "https://am.ticketmaster.com/tiff/",
    "source": "TIFF Bell Lightbox"
  },
  {
    "title": "Jimpa - Sophie Hyde",
    "showtime": "Saturday, February 28, 6:30PM",
    "link": "https://am.ticketmaster.com/tiff/ism/NkYyODYzVDI=",
    "source": "TIFF Bell Lightbox"
  },
  {
    "title": "Jimpa - Sophie Hyde",
    "showtime": "Saturday, February 28, 9:15PM",
    "link": "https://am.ticketmaster.com/tiff/ism/NkYyODkxVDI=",
    "source": "TIFF Bell Lightbox"
  },
  {
    "title": "Les années déclic preceded by Jan Palach",
    "showtime": "Saturday, February 28, 6:45PM",
    "link": "https://am.ticketmaster.com/tiff/ism/NkYyODY0VDQ=",
    "source": "TIFF Bell Lightbox"
  },
  {
    "title": "Montreal, My Beautiful - Xiaodan He",
    "showtime": "Saturday, February 28, 12:15PM",
    "link": "https://am.ticketmaster.com/tiff/ism/NkYyOEwxVDU=",
    "source": "TIFF Bell Lightbox"
  },
  {
    "title": "Montreal, My Beautiful - Xiaodan He",
    "showtime": "Saturday, February 28, 9:00PM",
    "link": "https://am.ticketmaster.com/tiff/ism/NkYyODkwVDU=",
    "source": "TIFF Bell Lightbox"
  },
  {
    "title": "Pillion - Harry Lighton",
    "showtime": "Saturday, February 28, 12:45PM",
    "link": "https://am.ticketmaster.com/tiff/ism/NkYyOEw0VDM=",
    "source": "TIFF Bell Lightbox"
  },
  {
    "title": "Sirāt - Oliver Laxe",
    "showtime": "Saturday, February 28, 3:30PM",
    "link": "https://am.ticketmaster.com/tiff/ism/NkYyODMzVDI=",
    "source": "TIFF Bell Lightbox"
  },
  {
    "title": "Sirāt - Oliver Laxe",
    "showtime": "Saturday, February 28, 6:15PM",
    "link": "https://am.ticketmaster.com/tiff/ism/NkYyODYxVDU=",
    "source": "TIFF Bell Lightbox"
  },
  {
    "title": "Sirāt - Oliver Laxe",
    "showtime": "Saturday, February 28, 9:30PM",
    "link": "https://am.ticketmaster.com/tiff/ism/NkYyODkzVDQ=",
    "source": "TIFF Bell Lightbox"
  },
  {
    "title": "The President's Cake - Hasan Hadi",
    "showtime": "Saturday, February 28, 1:30PM",
    "link": "https://am.ticketmaster.com/tiff/ism/NkYyODEzVDQ=",
    "source": "TIFF Bell Lightbox"
  },
  {
    "title": "The President's Cake - Hasan Hadi",
    "showtime": "Saturday, February 28, 6:00PM",
    "link": "https://am.ticketmaster.com/tiff/ism/NkYyODYwVDM=",
    "source": "TIFF Bell Lightbox"
  },
  {
    "title": "2026 Oscar-Nominated Short Films: Animated",
    "showtime": "Sunday, March 1, 2:00PM",
    "link": "https://am.ticketmaster.com/tiff/ism/Nk0wMTIwVDE=",
    "source": "TIFF Bell Lightbox"
  },
  {
    "title": "2026 Oscar-Nominated Short Films: Animated",
    "showtime": "Sunday, March 1, 6:00PM",
    "link": "https://am.ticketmaster.com/tiff/ism/Nk0wMTYwVDU=",
    "source": "TIFF Bell Lightbox"
  },
  {
    "title": "2026 Oscar-Nominated Short Films: Documentary",
    "showtime": "Sunday, March 1, 12:00PM",
    "link": "https://am.ticketmaster.com/tiff/ism/Nk0wMUwwVDI=",
    "source": "TIFF Bell Lightbox"
  },
  {
    "title": "2026 Oscar-Nominated Short Films: Documentary",
    "showtime": "Sunday, March 1, 7:15PM",
    "link": "https://am.ticketmaster.com/tiff/ism/Nk0wMTcxVDE=",
    "source": "TIFF Bell Lightbox"
  },
  {
    "title": "2026 Oscar-Nominated Short Films: Live Action",
    "showtime": "Sunday, March 1, 4:15PM",
    "link": "https://am.ticketmaster.com/tiff/ism/Nk0wMTQxVDE=",
    "source": "TIFF Bell Lightbox"
  },
  {
    "title": "2026 Oscar-Nominated Short Films: Live Action",
    "showtime": "Sunday, March 1, 8:15PM",
    "link": "https://am.ticketmaster.com/tiff/ism/Nk0wMTgxVDU=",
    "source": "TIFF Bell Lightbox"
  },
  {
    "title": "All That's Left of You - Cherien Dabis",
    "showtime": "Sunday, March 1, 12:05PM",
    "link": "https://am.ticketmaster.com/tiff/ism/Nk0wMUwwVDU=",
    "source": "TIFF Bell Lightbox"
  },
  {
    "title": "All That's Left of You - Cherien Dabis",
    "showtime": "Sunday, March 1, 9:15PM",
    "link": "https://am.ticketmaster.com/tiff/ism/Nk0wMTkxVDQ=",
    "source": "TIFF Bell Lightbox"
  },
  {
    "title": "International Cinema Cafe",
    "showtime": "Sunday, March 1, 10:30AM",
    "link": "https://am.ticketmaster.com/tiff/buy/ism/Nk0wMUozVDE=",
    "source": "TIFF Bell Lightbox"
  },
  {
    "title": "Jean-Luc Godard à la Cinémathèque française - Various filmmakers",
    "showtime": "Sunday, March 1, 4:00PM",
    "link": "https://am.ticketmaster.com/tiff/ism/Nk0wMTQwVDQ=",
    "source": "TIFF Bell Lightbox"
  },
  {
    "title": "Jimpa - Sophie Hyde",
    "showtime": "Sunday, March 1, 12:45PM",
    "link": "https://am.ticketmaster.com/tiff/ism/Nk0wMUw0VDM=",
    "source": "TIFF Bell Lightbox"
  },
  {
    "title": "Jimpa - Sophie Hyde",
    "showtime": "Sunday, March 1, 6:45PM",
    "link": "https://am.ticketmaster.com/tiff/ism/Nk0wMTY0VDI=",
    "source": "TIFF Bell Lightbox"
  },
  {
    "title": "Montreal, My Beautiful - Xiaodan He",
    "showtime": "Sunday, March 1, 3:15PM",
    "link": "https://am.ticketmaster.com/tiff/ism/Nk0wMTMxVDU=",
    "source": "TIFF Bell Lightbox"
  },
  {
    "title": "Pillion - Harry Lighton",
    "showtime": "Sunday, March 1, 8:45PM",
    "link": "https://am.ticketmaster.com/tiff/ism/Nk0wMTg0VDM=",
    "source": "TIFF Bell Lightbox"
  },
  {
    "title": "Reporters with Gaëlle Morel",
    "showtime": "Sunday, March 1, 6:30PM",
    "link": "https://am.ticketmaster.com/tiff/ism/Nk0wMTYzVDQ=",
    "source": "TIFF Bell Lightbox"
  },
  {
    "title": "Sirāt - Oliver Laxe",
    "showtime": "Sunday, March 1, 3:45PM",
    "link": "https://am.ticketmaster.com/tiff/ism/Nk0wMTM0VDI=",
    "source": "TIFF Bell Lightbox"
  },
  {
    "title": "Sirāt - Oliver Laxe",
    "showtime": "Sunday, March 1, 9:30PM",
    "link": "https://am.ticketmaster.com/tiff/ism/Nk0wMTkzVDI=",
    "source": "TIFF Bell Lightbox"
  },
  {
    "title": "The President's Cake - Hasan Hadi",
    "showtime": "Sunday, March 1, 12:30PM",
    "link": "https://am.ticketmaster.com/tiff/ism/Nk0wMUwzVDQ=",
    "source": "TIFF Bell Lightbox"
  },
  {
    "title": "The President's Cake - Hasan Hadi",
    "showtime": "Sunday, March 1, 6:15PM",
    "link": "https://am.ticketmaster.com/tiff/ism/Nk0wMTYxVDM=",
    "source": "TIFF Bell Lightbox"
  },
  {
    "title": "Zootopia 2 - Byron Howard, Jared Bush",
    "showtime": "Sunday, March 1, 3:30PM",
    "link": "https://am.ticketmaster.com/tiff/ism/Nk0wMTMzVDM=",
    "source": "TIFF Bell Lightbox"
  },
  {
    "title": "2026 Oscar-Nominated Short Films: Animated",
    "showtime": "Tuesday, March 3, 5:00PM",
    "link": "https://am.ticketmaster.com/tiff/ism/Nk0wMzUwVDE=",
    "source": "TIFF Bell Lightbox"
  },
  {
    "title": "2026 Oscar-Nominated Short Films: Documentary",
    "showtime": "Tuesday, March 3, 8:30PM",
    "link": "https://am.ticketmaster.com/tiff/ism/Nk0wMzgzVDU=",
    "source": "TIFF Bell Lightbox"
  },
  {
    "title": "2026 Oscar-Nominated Short Films: Live Action",
    "showtime": "Tuesday, March 3, 7:05PM",
    "link": "https://am.ticketmaster.com/tiff/ism/Nk0wMzcwVDE=",
    "source": "TIFF Bell Lightbox"
  },
  {
    "title": "All That's Left of You - Cherien Dabis",
    "showtime": "Tuesday, March 3, 5:15PM",
    "link": "https://am.ticketmaster.com/tiff/ism/Nk0wMzUxVDU=",
    "source": "TIFF Bell Lightbox"
  },
  {
    "title": "Film Reference Library Public Hours",
    "showtime": "Tuesday, March 3, 12:00PM",
    "link": "https://am.ticketmaster.com/tiff/",
    "source": "TIFF Bell Lightbox"
  },
  {
    "title": "Jimpa - Sophie Hyde",
    "showtime": "Tuesday, March 3, 8:45PM",
    "link": "https://am.ticketmaster.com/tiff/ism/Nk0wMzg0VDM=",
    "source": "TIFF Bell Lightbox"
  },
  {
    "title": "Sirāt - Oliver Laxe",
    "showtime": "Tuesday, March 3, 9:50PM",
    "link": "https://am.ticketmaster.com/tiff/ism/Nk0wMzk1VDE=",
    "source": "TIFF Bell Lightbox"
  },
  {
    "title": "The President's Cake - Hasan Hadi",
    "showtime": "Tuesday, March 3, 6:15PM",
    "link": "https://am.ticketmaster.com/tiff/ism/Nk0wMzYxVDM=",
    "source": "TIFF Bell Lightbox"
  },
  {
    "title": "The Wind Will Carry Us, with Cameron Bailey",
    "showtime": "Tuesday, March 3, 6:00PM",
    "link": "https://am.ticketmaster.com/tiff/ism/Nk0wMzYwVDI=",
    "source": "TIFF Bell Lightbox"
  },
  {
    "title": "2026 Oscar-Nominated Short Films: Animated",
    "showtime": "Wednesday, March 4, 4:05PM",
    "link": "https://am.ticketmaster.com/tiff/ism/Nk0wNDQwVDI=",
    "source": "TIFF Bell Lightbox"
  },
  {
    "title": "2026 Oscar-Nominated Short Films: Documentary",
    "showtime": "Wednesday, March 4, 7:15PM",
    "link": "https://am.ticketmaster.com/tiff/ism/Nk0wNDcxVDU=",
    "source": "TIFF Bell Lightbox"
  },
  {
    "title": "2026 Oscar-Nominated Short Films: Live Action",
    "showtime": "Wednesday, March 4, 4:00PM",
    "link": "https://am.ticketmaster.com/tiff/ism/Nk0wNDQwVDQ=",
    "source": "TIFF Bell Lightbox"
  },
  {
    "title": "All That's Left of You - Cherien Dabis",
    "showtime": "Wednesday, March 4, 9:15PM",
    "link": "https://am.ticketmaster.com/tiff/ism/Nk0wNDkxVDQ=",
    "source": "TIFF Bell Lightbox"
  },
  {
    "title": "Film Reference Library Public Hours",
    "showtime": "Wednesday, March 4, 12:00PM",
    "link": "https://am.ticketmaster.com/tiff/",
    "source": "TIFF Bell Lightbox"
  },
  {
    "title": "Jimpa - Sophie Hyde",
    "showtime": "Wednesday, March 4, 6:45PM",
    "link": "https://am.ticketmaster.com/tiff/ism/Nk0wNDY0VDE=",
    "source": "TIFF Bell Lightbox"
  },
  {
    "title": "Millennium Actress - Satoshi Kon",
    "showtime": "Wednesday, March 4, 6:30PM",
    "link": "https://am.ticketmaster.com/tiff/ism/Nk0wNDYzVDI=",
    "source": "TIFF Bell Lightbox"
  },
  {
    "title": "Montreal, My Beautiful - Xiaodan He",
    "showtime": "Wednesday, March 4, 9:30PM",
    "link": "https://am.ticketmaster.com/tiff/ism/Nk0wNDkzVDE=",
    "source": "TIFF Bell Lightbox"
  },
  {
    "title": "Pillion - Harry Lighton",
    "showtime": "Wednesday, March 4, 6:40PM",
    "link": "https://am.ticketmaster.com/tiff/ism/Nk0wNDY0VDQ=",
    "source": "TIFF Bell Lightbox"
  },
  {
    "title": "Sirāt - Oliver Laxe",
    "showtime": "Wednesday, March 4, 4:30PM",
    "link": "https://am.ticketmaster.com/tiff/ism/Nk0wNDQzVDU=",
    "source": "TIFF Bell Lightbox"
  },
  {
    "title": "Sirāt - Oliver Laxe",
    "showtime": "Wednesday, March 4, 9:20PM",
    "link": "https://am.ticketmaster.com/tiff/ism/Nk0wNDkyVDI=",
    "source": "TIFF Bell Lightbox"
  },
  {
    "title": "The President's Cake - Hasan Hadi",
    "showtime": "Wednesday, March 4, 4:15PM",
    "link": "https://am.ticketmaster.com/tiff/ism/Nk0wNDQxVDE=",
    "source": "TIFF Bell Lightbox"
  },
  {
    "title": "10e Chambre, instants d’audience - Raymond Depardon",
    "showtime": "Thursday, March 5, 6:30PM",
    "link": "https://am.ticketmaster.com/tiff/ism/Nk0wNTYzVDM=",
    "source": "TIFF Bell Lightbox"
  },
  {
    "title": "2026 Oscar-Nominated Short Films: Animated",
    "showtime": "Thursday, March 5, 3:50PM",
    "link": "https://am.ticketmaster.com/tiff/ism/Nk0wNTM1VDI=",
    "source": "TIFF Bell Lightbox"
  },
  {
    "title": "2026 Oscar-Nominated Short Films: Documentary",
    "showtime": "Thursday, March 5, 8:55PM",
    "link": "https://am.ticketmaster.com/tiff/ism/Nk0wNTg1VDM=",
    "source": "TIFF Bell Lightbox"
  },
  {
    "title": "2026 Oscar-Nominated Short Films: Live Action",
    "showtime": "Thursday, March 5, 7:10PM",
    "link": "https://am.ticketmaster.com/tiff/ism/Nk0wNTcxVDU=",
    "source": "TIFF Bell Lightbox"
  },
  {
    "title": "All That's Left of You - Cherien Dabis",
    "showtime": "Thursday, March 5, 4:00PM",
    "link": "https://am.ticketmaster.com/tiff/ism/Nk0wNTQwVDU=",
    "source": "TIFF Bell Lightbox"
  },
  {
    "title": "Film Reference Library Public Hours",
    "showtime": "Thursday, March 5, 12:00PM",
    "link": "https://am.ticketmaster.com/tiff/",
    "source": "TIFF Bell Lightbox"
  },
  {
    "title": "Jimpa - Sophie Hyde",
    "showtime": "Thursday, March 5, 8:30PM",
    "link": "https://am.ticketmaster.com/tiff/ism/Nk0wNTgzVDI=",
    "source": "TIFF Bell Lightbox"
  },
  {
    "title": "Montreal, My Beautiful - Xiaodan He",
    "showtime": "Thursday, March 5, 3:45PM",
    "link": "https://am.ticketmaster.com/tiff/ism/Nk0wNTM0VDM=",
    "source": "TIFF Bell Lightbox"
  },
  {
    "title": "Sinners - Ryan Coogler",
    "showtime": "Thursday, March 5, 9:30PM",
    "link": "https://am.ticketmaster.com/tiff/ism/Nk0wNTkzVDE=",
    "source": "TIFF Bell Lightbox"
  },
  {
    "title": "Sirāt - Oliver Laxe",
    "showtime": "Thursday, March 5, 9:50PM",
    "link": "https://am.ticketmaster.com/tiff/ism/Nk0wNTk1VDU=",
    "source": "TIFF Bell Lightbox"
  },
  {
    "title": "The President's Cake - Hasan Hadi",
    "showtime": "Thursday, March 5, 6:00PM",
    "link": "https://am.ticketmaster.com/tiff/ism/Nk0wNTYwVDI=",
    "source": "TIFF Bell Lightbox"
  },
  {
    "title": "Faits divers - Raymond Depardon",
    "showtime": "Friday, March 6, 6:30PM",
    "link": "https://am.ticketmaster.com/tiff/ism/Nk0wNjYzVDQ=",
    "source": "TIFF Bell Lightbox"
  },
  {
    "title": "Film Reference Library Public Hours",
    "showtime": "Friday, March 6, 12:00PM",
    "link": "https://am.ticketmaster.com/tiff/",
    "source": "TIFF Bell Lightbox"
  },
  {
    "title": "Peaky Blinders: The Immortal Man - Tom Harper",
    "showtime": "Friday, March 6, 2:00PM",
    "link": "https://am.ticketmaster.com/tiff/ism/Nk0wNjIwVDE=",
    "source": "TIFF Bell Lightbox"
  },
  {
    "title": "Peaky Blinders: The Immortal Man - Tom Harper",
    "showtime": "Friday, March 6, 4:15PM",
    "link": "https://am.ticketmaster.com/tiff/ism/Nk0wNjQxVDE=",
    "source": "TIFF Bell Lightbox"
  },
  {
    "title": "Peaky Blinders: The Immortal Man - Tom Harper",
    "showtime": "Friday, March 6, 7:15PM",
    "link": "https://am.ticketmaster.com/tiff/ism/Nk0wNjcxVDM=",
    "source": "TIFF Bell Lightbox"
  },
  {
    "title": "Peaky Blinders: The Immortal Man - Tom Harper",
    "showtime": "Friday, March 6, 9:30PM",
    "link": "https://am.ticketmaster.com/tiff/ism/Nk0wNjkzVDM=",
    "source": "TIFF Bell Lightbox"
  },
  {
    "title": "A Thousand and One - A.V. Rockwell",
    "showtime": "Saturday, March 7, 3:30PM",
    "link": "https://am.ticketmaster.com/tiff/ism/Nk0wNzMzVDQ=",
    "source": "TIFF Bell Lightbox"
  },
  {
    "title": "Film Reference Library Public Hours",
    "showtime": "Saturday, March 7, 12:00PM",
    "link": "https://am.ticketmaster.com/tiff/",
    "source": "TIFF Bell Lightbox"
  },
  {
    "title": "Peaky Blinders: The Immortal Man - Tom Harper",
    "showtime": "Saturday, March 7, 1:30PM",
    "link": "https://am.ticketmaster.com/tiff/ism/Nk0wNzEzVDI=",
    "source": "TIFF Bell Lightbox"
  },
  {
    "title": "Peaky Blinders: The Immortal Man - Tom Harper",
    "showtime": "Saturday, March 7, 3:45PM",
    "link": "https://am.ticketmaster.com/tiff/ism/Nk0wNzM0VDI=",
    "source": "TIFF Bell Lightbox"
  },
  {
    "title": "Peaky Blinders: The Immortal Man - Tom Harper",
    "showtime": "Saturday, March 7, 6:00PM",
    "link": "https://am.ticketmaster.com/tiff/ism/Nk0wNzYwVDI=",
    "source": "TIFF Bell Lightbox"
  },
  {
    "title": "Peaky Blinders: The Immortal Man - Tom Harper",
    "showtime": "Saturday, March 7, 9:00PM",
    "link": "https://am.ticketmaster.com/tiff/ism/Nk0wNzkwVDQ=",
    "source": "TIFF Bell Lightbox"
  },
  {
    "title": "Sinners - Ryan Coogler",
    "showtime": "Saturday, March 7, 7:30PM",
    "link": "https://am.ticketmaster.com/tiff/ism/Nk0wNzczVDE=",
    "source": "TIFF Bell Lightbox"
  },
  {
    "title": "Urgences - Raymond Depardon",
    "showtime": "Saturday, March 7, 6:30PM",
    "link": "https://am.ticketmaster.com/tiff/ism/Nk0wNzYzVDQ=",
    "source": "TIFF Bell Lightbox"
  },
  {
    "title": "Délits flagrants - Raymond Depardon",
    "showtime": "Sunday, March 8, 6:30PM",
    "link": "https://am.ticketmaster.com/tiff/ism/Nk0wODYzVDQ=",
    "source": "TIFF Bell Lightbox"
  },
  {
    "title": "F1: The Movie - Joseph Kosinski",
    "showtime": "Sunday, March 8, 8:30PM",
    "link": "https://am.ticketmaster.com/tiff/ism/Nk0wODgzVDI=",
    "source": "TIFF Bell Lightbox"
  },
  {
    "title": "Little Amélie or the Character of Rain - Maïlys Vallade, Liane-Cho Han",
    "showtime": "Sunday, March 8, 3:00PM",
    "link": "https://am.ticketmaster.com/tiff/ism/Nk0wODMwVDU=",
    "source": "TIFF Bell Lightbox"
  },
  {
    "title": "Peaky Blinders: The Immortal Man - Tom Harper",
    "showtime": "Sunday, March 8, 1:00PM",
    "link": "https://am.ticketmaster.com/tiff/ism/Nk0wODEwVDI=",
    "source": "TIFF Bell Lightbox"
  },
  {
    "title": "Peaky Blinders: The Immortal Man - Tom Harper",
    "showtime": "Sunday, March 8, 3:45PM",
    "link": "https://am.ticketmaster.com/tiff/ism/Nk0wODM0VDE=",
    "source": "TIFF Bell Lightbox"
  },
  {
    "title": "Peaky Blinders: The Immortal Man - Tom Harper",
    "showtime": "Sunday, March 8, 6:15PM",
    "link": "https://am.ticketmaster.com/tiff/ism/Nk0wODYxVDI=",
    "source": "TIFF Bell Lightbox"
  },
  {
    "title": "Peaky Blinders: The Immortal Man - Tom Harper",
    "showtime": "Sunday, March 8, 9:00PM",
    "link": "https://am.ticketmaster.com/tiff/ism/Nk0wODkwVDQ=",
    "source": "TIFF Bell Lightbox"
  },
  {
    "title": "The Girls - Sumitra Peries",
    "showtime": "Sunday, March 8, 3:30PM",
    "link": "https://am.ticketmaster.com/tiff/ism/Nk0wODMzVDQ=",
    "source": "TIFF Bell Lightbox"
  },
  {
    "title": "Film Reference Library Public Hours",
    "showtime": "Tuesday, March 10, 12:00PM",
    "link": "https://am.ticketmaster.com/tiff/",
    "source": "TIFF Bell Lightbox"
  },
  {
    "title": "Monsieur Lazhar - Philippe Falardeau",
    "showtime": "Tuesday, March 10, 6:30PM",
    "link": "https://am.ticketmaster.com/tiff/ism/Nk0xMDYzVDM=",
    "source": "TIFF Bell Lightbox"
  },
  {
    "title": "Peaky Blinders: The Immortal Man - Tom Harper",
    "showtime": "Tuesday, March 10, 6:45PM",
    "link": "https://am.ticketmaster.com/tiff/ism/Nk0xMDY0VDI=",
    "source": "TIFF Bell Lightbox"
  },
  {
    "title": "Secret Movie Club",
    "showtime": "Tuesday, March 10, 7:00PM",
    "link": "https://am.ticketmaster.com/tiff/buy/ism/Nk0xMDcwVDE=",
    "source": "TIFF Bell Lightbox"
  },
  {
    "title": "China Town with Lucy Raven",
    "showtime": "Wednesday, March 11, 6:30PM",
    "link": "https://am.ticketmaster.com/tiff/ism/Nk0xMTYzVDQ=",
    "source": "TIFF Bell Lightbox"
  },
  {
    "title": "Film Reference Library Public Hours",
    "showtime": "Wednesday, March 11, 12:00PM",
    "link": "https://am.ticketmaster.com/tiff/",
    "source": "TIFF Bell Lightbox"
  },
  {
    "title": "Peaky Blinders: The Immortal Man - Tom Harper",
    "showtime": "Wednesday, March 11, 4:15PM",
    "link": "https://am.ticketmaster.com/tiff/ism/Nk0xMTQxVDE=",
    "source": "TIFF Bell Lightbox"
  },
  {
    "title": "Peaky Blinders: The Immortal Man - Tom Harper",
    "showtime": "Wednesday, March 11, 6:45PM",
    "link": "https://am.ticketmaster.com/tiff/ism/Nk0xMTY0VDI=",
    "source": "TIFF Bell Lightbox"
  },
  {
    "title": "Peaky Blinders: The Immortal Man - Tom Harper",
    "showtime": "Wednesday, March 11, 9:00PM",
    "link": "https://am.ticketmaster.com/tiff/ism/Nk0xMTkwVDI=",
    "source": "TIFF Bell Lightbox"
  },
  {
    "title": "Film Reference Library Public Hours",
    "showtime": "Thursday, March 12, 12:00PM",
    "link": "https://am.ticketmaster.com/tiff/",
    "source": "TIFF Bell Lightbox"
  },
  {
    "title": "Peaky Blinders: The Immortal Man - Tom Harper",
    "showtime": "Thursday, March 12, 4:00PM",
    "link": "https://am.ticketmaster.com/tiff/ism/Nk0xMjQwVDE=",
    "source": "TIFF Bell Lightbox"
  },
  {
    "title": "Peaky Blinders: The Immortal Man - Tom Harper",
    "showtime": "Thursday, March 12, 7:30PM",
    "link": "https://am.ticketmaster.com/tiff/ism/Nk0xMjczVDI=",
    "source": "TIFF Bell Lightbox"
  },
  {
    "title": "Peaky Blinders: The Immortal Man - Tom Harper",
    "showtime": "Thursday, March 12, 10:00PM",
    "link": "https://am.ticketmaster.com/tiff/ism/Nk0xMjAwVDQ=",
    "source": "TIFF Bell Lightbox"
  },
  {
    "title": "Sinners - Ryan Coogler",
    "showtime": "Thursday, March 12, 7:15PM",
    "link": "https://am.ticketmaster.com/tiff/ism/Nk0xMjcxVDE=",
    "source": "TIFF Bell Lightbox"
  },
  {
    "title": "The Beirut Trilogy",
    "showtime": "Thursday, March 12, 6:30PM",
    "link": "https://am.ticketmaster.com/tiff/ism/Nk0xMjYzVDQ=",
    "source": "TIFF Bell Lightbox"
  },
  {
    "title": "Film Reference Library Public Hours",
    "showtime": "Friday, March 13, 12:00PM",
    "link": "https://am.ticketmaster.com/tiff/",
    "source": "TIFF Bell Lightbox"
  },
  {
    "title": "The Razor's Edge preceded by Children of War",
    "showtime": "Friday, March 13, 6:30PM",
    "link": "https://am.ticketmaster.com/tiff/ism/Nk0xMzYzVDQ=",
    "source": "TIFF Bell Lightbox"
  },
  {
    "title": "Film Reference Library Public Hours",
    "showtime": "Saturday, March 14, 12:00PM (Free)",
    "link": "https://tiff.net/events/film-reference-library-public-hours",
    "source": "TIFF Bell Lightbox"
  },
  {
    "title": "Jocelyne Saab: Utopia Lost",
    "showtime": "Saturday, March 14, 3:30PM",
    "link": "https://am.ticketmaster.com/tiff/ism/Nk0xNDMzVDQ=",
    "source": "TIFF Bell Lightbox"
  },
  {
    "title": "Sing Along: Encanto",
    "showtime": "Saturday, March 14, 1:00PM",
    "link": "https://am.ticketmaster.com/tiff/ism/Nk0xNDEwVDI=",
    "source": "TIFF Bell Lightbox"
  },
  {
    "title": "The Vanishing Point with Bani Khoshnoudi",
    "showtime": "Saturday, March 14, 6:30PM",
    "link": "https://am.ticketmaster.com/tiff/ism/Nk0xNDYzVDQ=",
    "source": "TIFF Bell Lightbox"
  },
  {
    "title": "Inherent Vice - Paul Thomas Anderson",
    "showtime": "Sunday, March 15, 11:30AM",
    "link": "https://am.ticketmaster.com/tiff/",
    "source": "TIFF Bell Lightbox"
  },
  {
    "title": "Palestine and \"The Fatah Land\"",
    "showtime": "Sunday, March 15, 2:30PM",
    "link": "https://am.ticketmaster.com/tiff/ism/Nk0xNTIzVDM=",
    "source": "TIFF Bell Lightbox"
  },
  {
    "title": "TIFF Oscars Celebration",
    "showtime": "Sunday, March 15, 5:30PM",
    "link": "https://am.ticketmaster.com/tiff/buy/quickbuy?id=NTc4NQ==",
    "source": "TIFF Bell Lightbox"
  },
  {
    "title": "TIFF Oscars Member Watch Party",
    "showtime": "Sunday, March 15, 7:00PM",
    "link": "https://am.ticketmaster.com/tiff/buy/quickbuy?id=NTc4Mw==",
    "source": "TIFF Bell Lightbox"
  },
  {
    "title": "Film Reference Library Public Hours",
    "showtime": "Tuesday, March 17, 12:00PM (Free)",
    "link": "https://tiff.net/events/film-reference-library-public-hours",
    "source": "TIFF Bell Lightbox"
  },
  {
    "title": "San Clemente - Raymond Depardon, Sophie Ristelhueber",
    "showtime": "Tuesday, March 17, 6:30PM",
    "link": "https://am.ticketmaster.com/tiff/ism/Nk0xNzYzVDQ=",
    "source": "TIFF Bell Lightbox"
  },
  {
    "title": "Film Reference Library Public Hours",
    "showtime": "Wednesday, March 18, 12:00PM (Free)",
    "link": "https://tiff.net/events/film-reference-library-public-hours",
    "source": "TIFF Bell Lightbox"
  },
  {
    "title": "How to Craft a Standout Submission and Make the Most of Creators’ Labs at TIFF: The Market",
    "showtime": "Wednesday, March 18, 5:00PM",
    "link": "https://am.ticketmaster.com/tiff/ism/Nk0xODUwVDQ=",
    "source": "TIFF Bell Lightbox"
  },
  {
    "title": "Songs My Brothers Taught Me - Chloé Zhao",
    "showtime": "Wednesday, March 18, 7:00PM",
    "link": "https://am.ticketmaster.com/tiff/ism/Nk0xODcwVDQ=",
    "source": "TIFF Bell Lightbox"
  },
  {
    "title": "Film Reference Library Public Hours",
    "showtime": "Thursday, March 19, 12:00PM (Free)",
    "link": "https://tiff.net/events/film-reference-library-public-hours",
    "source": "TIFF Bell Lightbox"
  },
  {
    "title": "Idiotka - Nastasya Popov",
    "showtime": "Thursday, March 19, 7:00PM",
    "link": "https://am.ticketmaster.com/tiff/ism/Nk0xOTcwVDM=",
    "source": "TIFF Bell Lightbox"
  },
  {
    "title": "Les révolutionnaires du Tchad preceded by Tibesti Too",
    "showtime": "Thursday, March 19, 6:30PM",
    "link": "https://am.ticketmaster.com/tiff/ism/Nk0xOTYzVDQ=",
    "source": "TIFF Bell Lightbox"
  },
  {
    "title": "Film Reference Library Public Hours",
    "showtime": "Friday, March 20, 12:00PM (Free)",
    "link": "https://tiff.net/events/film-reference-library-public-hours",
    "source": "TIFF Bell Lightbox"
  },
  {
    "title": "Once Upon a Time in Beirut - Jocelyne Saab",
    "showtime": "Friday, March 20, 6:30PM",
    "link": "https://am.ticketmaster.com/tiff/ism/Nk0yMDYzVDQ=",
    "source": "TIFF Bell Lightbox"
  },
  {
    "title": "1974, une partie de campagne - Raymond Depardon",
    "showtime": "Saturday, March 21, 6:30PM",
    "link": "https://am.ticketmaster.com/tiff/ism/Nk0yMTYzVDQ=",
    "source": "TIFF Bell Lightbox"
  },
  {
    "title": "Film Reference Library Public Hours",
    "showtime": "Saturday, March 21, 12:00PM (Free)",
    "link": "https://tiff.net/events/film-reference-library-public-hours",
    "source": "TIFF Bell Lightbox"
  },
  {
    "title": "Jocelyne Saab: Blind Faith",
    "showtime": "Saturday, March 21, 4:00PM",
    "link": "https://am.ticketmaster.com/tiff/ism/Nk0yMTQwVDQ=",
    "source": "TIFF Bell Lightbox"
  },
  {
    "title": "La captive du désert - Raymond Depardon",
    "showtime": "Sunday, March 22, 3:15PM",
    "link": "https://am.ticketmaster.com/tiff/ism/Nk0yMjMxVDQ=",
    "source": "TIFF Bell Lightbox"
  },
  {
    "title": "Nahla followed by On the Set of Nahla",
    "showtime": "Sunday, March 22, 6:30PM",
    "link": "https://am.ticketmaster.com/tiff/ism/Nk0yMjYzVDQ=",
    "source": "TIFF Bell Lightbox"
  },
  {
    "title": "Conversation Piece - Luchino Visconti",
    "showtime": "Tuesday, March 24, 6:30PM",
    "link": "https://am.ticketmaster.com/tiff/ism/Nk0yNDYzVDQ=",
    "source": "TIFF Bell Lightbox"
  },
  {
    "title": "Film Reference Library Public Hours",
    "showtime": "Tuesday, March 24, 12:00PM (Free)",
    "link": "https://tiff.net/events/film-reference-library-public-hours",
    "source": "TIFF Bell Lightbox"
  },
  {
    "title": "Damnation - Béla Tarr",
    "showtime": "Wednesday, March 25, 6:30PM",
    "link": "https://am.ticketmaster.com/tiff/ism/Nk0yNTYzVDQ=",
    "source": "TIFF Bell Lightbox"
  },
  {
    "title": "Film Reference Library Public Hours",
    "showtime": "Wednesday, March 25, 12:00PM (Free)",
    "link": "https://tiff.net/events/film-reference-library-public-hours",
    "source": "TIFF Bell Lightbox"
  },
  {
    "title": "Mississippi Masala preceded by One Day",
    "showtime": "Wednesday, March 25, 6:00PM",
    "link": "https://am.ticketmaster.com/tiff/ism/Nk0yNTYwVDM=",
    "source": "TIFF Bell Lightbox"
  },
  {
    "title": "Film Reference Library Public Hours",
    "showtime": "Thursday, March 26, 12:00PM (Free)",
    "link": "https://tiff.net/events/film-reference-library-public-hours",
    "source": "TIFF Bell Lightbox"
  },
  {
    "title": "Idiotka - Nastasya Popov",
    "showtime": "Thursday, March 26, 8:45PM",
    "link": "https://am.ticketmaster.com/tiff/ism/Nk0yNjg0VDQ=",
    "source": "TIFF Bell Lightbox"
  },
  {
    "title": "Profils paysans: L'approche - Raymond Depardon",
    "showtime": "Thursday, March 26, 6:30PM",
    "link": "https://am.ticketmaster.com/tiff/ism/Nk0yNjYzVDQ=",
    "source": "TIFF Bell Lightbox"
  },
  {
    "title": "Setting the Scene Exhibition Launch",
    "showtime": "Thursday, March 26, 5:00PM (Free)",
    "link": "https://tiff.net/events/setting-the-scene-exhibition-launch",
    "source": "TIFF Bell Lightbox"
  },
  {
    "title": "Film Reference Library Public Hours",
    "showtime": "Friday, March 27, 12:00PM (Free)",
    "link": "https://tiff.net/events/film-reference-library-public-hours",
    "source": "TIFF Bell Lightbox"
  },
  {
    "title": "Profils paysans: Le quotidien preceded by Quoi de neuf au Garet ?",
    "showtime": "Friday, March 27, 6:30PM",
    "link": "https://am.ticketmaster.com/tiff/ism/Nk0yNzYzVDQ=",
    "source": "TIFF Bell Lightbox"
  },
  {
    "title": "Setting the Scene Exhibition",
    "showtime": "Friday, March 27, 12:00PM (Free)",
    "link": "https://tiff.net/events/setting-the-scene-exhibition-open-hours",
    "source": "TIFF Bell Lightbox"
  },
  {
    "title": "Silver Screenings: The Queen of My Dreams",
    "showtime": "Friday, March 27, 12:00PM",
    "link": "https://am.ticketmaster.com/tiff/ism/Nk0yN0wwVDE=",
    "source": "TIFF Bell Lightbox"
  },
  {
    "title": "Conversation Piece - Luchino Visconti",
    "showtime": "Saturday, March 28, 3:30PM",
    "link": "https://am.ticketmaster.com/tiff/ism/Nk0yODMzVDQ=",
    "source": "TIFF Bell Lightbox"
  },
  {
    "title": "Film Reference Library Public Hours",
    "showtime": "Saturday, March 28, 12:00PM (Free)",
    "link": "https://tiff.net/events/film-reference-library-public-hours",
    "source": "TIFF Bell Lightbox"
  },
  {
    "title": "La vie moderne - Raymond Depardon",
    "showtime": "Saturday, March 28, 6:30PM",
    "link": "https://am.ticketmaster.com/tiff/ism/Nk0yODYzVDQ=",
    "source": "TIFF Bell Lightbox"
  },
  {
    "title": "International Cinema Cafe",
    "showtime": "Sunday, March 29, 10:30AM",
    "link": "https://am.ticketmaster.com/tiff/buy/ism/Nk0yOUozVDE=",
    "source": "TIFF Bell Lightbox"
  },
  {
    "title": "Paris preceded by New York, N.Y.",
    "showtime": "Sunday, March 29, 6:30PM",
    "link": "https://am.ticketmaster.com/tiff/ism/Nk0yOTYzVDQ=",
    "source": "TIFF Bell Lightbox"
  },
  {
    "title": "Wild Rose - Tom Harper",
    "showtime": "Sunday, March 29, 4:00PM",
    "link": "https://am.ticketmaster.com/tiff/ism/Nk0yOTQwVDQ=",
    "source": "TIFF Bell Lightbox"
  },
  {
    "title": "Film Reference Library Public Hours",
    "showtime": "Tuesday, March 31, 12:00PM (Free)",
    "link": "https://tiff.net/events/film-reference-library-public-hours",
    "source": "TIFF Bell Lightbox"
  },
  {
    "title": "Journal de France - Raymond Depardon, Claudine Nougaret",
    "showtime": "Tuesday, March 31, 6:30PM",
    "link": "https://am.ticketmaster.com/tiff/ism/Nk0zMTYzVDQ=",
    "source": "TIFF Bell Lightbox"
  },
  {
    "title": "Setting the Scene Exhibition",
    "showtime": "Tuesday, March 31, 12:00PM (Free)",
    "link": "https://tiff.net/events/setting-the-scene-exhibition-open-hours",
    "source": "TIFF Bell Lightbox"
  },
  {
    "title": "A New Love in Tokyo - Banmei Takahashi",
    "showtime": "Wednesday, April 1, 6:30PM",
    "link": "https://am.ticketmaster.com/tiff/ism/NkEwMTYzVDQ=",
    "source": "TIFF Bell Lightbox"
  },
  {
    "title": "Film Reference Library Public Hours",
    "showtime": "Wednesday, April 1, 12:00PM (Free)",
    "link": "https://tiff.net/events/film-reference-library-public-hours",
    "source": "TIFF Bell Lightbox"
  },
  {
    "title": "Setting the Scene Exhibition",
    "showtime": "Wednesday, April 1, 12:00PM (Free)",
    "link": "https://tiff.net/events/setting-the-scene-exhibition-open-hours",
    "source": "TIFF Bell Lightbox"
  },
  {
    "title": "Film Reference Library Public Hours",
    "showtime": "Thursday, April 2, 12:00PM (Free)",
    "link": "https://tiff.net/events/film-reference-library-public-hours",
    "source": "TIFF Bell Lightbox"
  },
  {
    "title": "Setting the Scene Exhibition",
    "showtime": "Thursday, April 2, 12:00PM (Free)",
    "link": "https://tiff.net/events/setting-the-scene-exhibition-open-hours",
    "source": "TIFF Bell Lightbox"
  },
  {
    "title": "What Does That Nature Say to You - Hong Sangsoo",
    "showtime": "Thursday, April 2, 6:30PM",
    "link": "https://am.ticketmaster.com/tiff/ism/NkEwMjYzVDQ=",
    "source": "TIFF Bell Lightbox"
  },
  {
    "title": "Film Reference Library Public Hours",
    "showtime": "Friday, April 3, 12:00PM (Free)",
    "link": "https://tiff.net/events/film-reference-library-public-hours",
    "source": "TIFF Bell Lightbox"
  },
  {
    "title": "Setting the Scene Exhibition",
    "showtime": "Friday, April 3, 12:00PM (Free)",
    "link": "https://tiff.net/events/setting-the-scene-exhibition-open-hours",
    "source": "TIFF Bell Lightbox"
  },
  {
    "title": "Film Reference Library Public Hours",
    "showtime": "Saturday, April 4, 12:00PM (Free)",
    "link": "https://tiff.net/events/film-reference-library-public-hours",
    "source": "TIFF Bell Lightbox"
  },
  {
    "title": "Setting the Scene Exhibition",
    "showtime": "Saturday, April 4, 12:00PM (Free)",
    "link": "https://tiff.net/events/setting-the-scene-exhibition-open-hours",
    "source": "TIFF Bell Lightbox"
  },
  {
    "title": "Film Reference Library Public Hours",
    "showtime": "Tuesday, April 7, 12:00PM (Free)",
    "link": "https://tiff.net/events/film-reference-library-public-hours",
    "source": "TIFF Bell Lightbox"
  },
  {
    "title": "Setting the Scene Exhibition",
    "showtime": "Tuesday, April 7, 12:00PM (Free)",
    "link": "https://tiff.net/events/setting-the-scene-exhibition-open-hours",
    "source": "TIFF Bell Lightbox"
  },
  {
    "title": "Film Reference Library Public Hours",
    "showtime": "Wednesday, April 8, 12:00PM (Free)",
    "link": "https://tiff.net/events/film-reference-library-public-hours",
    "source": "TIFF Bell Lightbox"
  },
  {
    "title": "Setting the Scene Exhibition",
    "showtime": "Wednesday, April 8, 12:00PM (Free)",
    "link": "https://tiff.net/events/setting-the-scene-exhibition-open-hours",
    "source": "TIFF Bell Lightbox"
  },
  {
    "title": "Film Reference Library Public Hours",
    "showtime": "Thursday, April 9, 12:00PM (Free)",
    "link": "https://tiff.net/events/film-reference-library-public-hours",
    "source": "TIFF Bell Lightbox"
  },
  {
    "title": "Setting the Scene Exhibition",
    "showtime": "Thursday, April 9, 12:00PM (Free)",
    "link": "https://tiff.net/events/setting-the-scene-exhibition-open-hours",
    "source": "TIFF Bell Lightbox"
  },
  {
    "title": "Film Reference Library Public Hours",
    "showtime": "Friday, April 10, 12:00PM (Free)",
    "link": "https://tiff.net/events/film-reference-library-public-hours",
    "source": "TIFF Bell Lightbox"
  },
  {
    "title": "Setting the Scene Exhibition",
    "showtime": "Friday, April 10, 12:00PM (Free)",
    "link": "https://tiff.net/events/setting-the-scene-exhibition-open-hours",
    "source": "TIFF Bell Lightbox"
  },
  {
    "title": "Film Reference Library Public Hours",
    "showtime": "Saturday, April 11, 12:00PM (Free)",
    "link": "https://tiff.net/events/film-reference-library-public-hours",
    "source": "TIFF Bell Lightbox"
  },
  {
    "title": "Setting the Scene Exhibition",
    "showtime": "Saturday, April 11, 12:00PM (Free)",
    "link": "https://tiff.net/events/setting-the-scene-exhibition-open-hours",
    "source": "TIFF Bell Lightbox"
  },
  {
    "title": "Film Reference Library Public Hours",
    "showtime": "Tuesday, April 14, 12:00PM (Free)",
    "link": "https://tiff.net/events/film-reference-library-public-hours",
    "source": "TIFF Bell Lightbox"
  },
  {
    "title": "Secret Movie Club",
    "showtime": "Tuesday, April 14, 7:00PM",
    "link": "https://am.ticketmaster.com/tiff/buy/ism/NkExNDcwVDE=",
    "source": "TIFF Bell Lightbox"
  },
  {
    "title": "Setting the Scene Exhibition",
    "showtime": "Tuesday, April 14, 12:00PM (Free)",
    "link": "https://tiff.net/events/setting-the-scene-exhibition-open-hours",
    "source": "TIFF Bell Lightbox"
  },
  {
    "title": "Film Reference Library Public Hours",
    "showtime": "Wednesday, April 15, 12:00PM (Free)",
    "link": "https://tiff.net/events/film-reference-library-public-hours",
    "source": "TIFF Bell Lightbox"
  },
  {
    "title": "Setting the Scene Exhibition",
    "showtime": "Wednesday, April 15, 12:00PM (Free)",
    "link": "https://tiff.net/events/setting-the-scene-exhibition-open-hours",
    "source": "TIFF Bell Lightbox"
  },
  {
    "title": "Film Reference Library Public Hours",
    "showtime": "Thursday, April 16, 12:00PM (Free)",
    "link": "https://tiff.net/events/film-reference-library-public-hours",
    "source": "TIFF Bell Lightbox"
  },
  {
    "title": "Setting the Scene Exhibition",
    "showtime": "Thursday, April 16, 12:00PM (Free)",
    "link": "https://tiff.net/events/setting-the-scene-exhibition-open-hours",
    "source": "TIFF Bell Lightbox"
  },
  {
    "title": "Film Reference Library Public Hours",
    "showtime": "Friday, April 17, 12:00PM (Free)",
    "link": "https://tiff.net/events/film-reference-library-public-hours",
    "source": "TIFF Bell Lightbox"
  },
  {
    "title": "Setting the Scene Exhibition",
    "showtime": "Friday, April 17, 12:00PM (Free)",
    "link": "https://tiff.net/events/setting-the-scene-exhibition-open-hours",
    "source": "TIFF Bell Lightbox"
  },
  {
    "title": "Film Reference Library Public Hours",
    "showtime": "Saturday, April 18, 12:00PM (Free)",
    "link": "https://tiff.net/events/film-reference-library-public-hours",
    "source": "TIFF Bell Lightbox"
  },
  {
    "title": "Setting the Scene Exhibition",
    "showtime": "Saturday, April 18, 12:00PM (Free)",
    "link": "https://tiff.net/events/setting-the-scene-exhibition-open-hours",
    "source": "TIFF Bell Lightbox"
  },
  {
    "title": "Film Reference Library Public Hours",
    "showtime": "Tuesday, April 21, 12:00PM (Free)",
    "link": "https://tiff.net/events/film-reference-library-public-hours",
    "source": "TIFF Bell Lightbox"
  },
  {
    "title": "Setting the Scene Exhibition",
    "showtime": "Tuesday, April 21, 12:00PM (Free)",
    "link": "https://tiff.net/events/setting-the-scene-exhibition-open-hours",
    "source": "TIFF Bell Lightbox"
  },
  {
    "title": "Film Reference Library Public Hours",
    "showtime": "Wednesday, April 22, 12:00PM (Free)",
    "link": "https://tiff.net/events/film-reference-library-public-hours",
    "source": "TIFF Bell Lightbox"
  },
  {
    "title": "Setting the Scene Exhibition",
    "showtime": "Wednesday, April 22, 12:00PM (Free)",
    "link": "https://tiff.net/events/setting-the-scene-exhibition-open-hours",
    "source": "TIFF Bell Lightbox"
  },
  {
    "title": "Film Reference Library Public Hours",
    "showtime": "Thursday, April 23, 12:00PM (Free)",
    "link": "https://tiff.net/events/film-reference-library-public-hours",
    "source": "TIFF Bell Lightbox"
  },
  {
    "title": "Setting the Scene Exhibition",
    "showtime": "Thursday, April 23, 12:00PM (Free)",
    "link": "https://tiff.net/events/setting-the-scene-exhibition-open-hours",
    "source": "TIFF Bell Lightbox"
  },
  {
    "title": "Film Reference Library Public Hours",
    "showtime": "Friday, April 24, 12:00PM (Free)",
    "link": "https://tiff.net/events/film-reference-library-public-hours",
    "source": "TIFF Bell Lightbox"
  },
  {
    "title": "Setting the Scene Exhibition",
    "showtime": "Friday, April 24, 12:00PM (Free)",
    "link": "https://tiff.net/events/setting-the-scene-exhibition-open-hours",
    "source": "TIFF Bell Lightbox"
  },
  {
    "title": "Film Reference Library Public Hours",
    "showtime": "Saturday, April 25, 12:00PM (Free)",
    "link": "https://tiff.net/events/film-reference-library-public-hours",
    "source": "TIFF Bell Lightbox"
  },
  {
    "title": "Setting the Scene Exhibition",
    "showtime": "Saturday, April 25, 12:00PM (Free)",
    "link": "https://tiff.net/events/setting-the-scene-exhibition-open-hours",
    "source": "TIFF Bell Lightbox"
  },
  {
    "title": "Film Reference Library Public Hours",
    "showtime": "Tuesday, April 28, 12:00PM (Free)",
    "link": "https://tiff.net/events/film-reference-library-public-hours",
    "source": "TIFF Bell Lightbox"
  },
  {
    "title": "Setting the Scene Exhibition",
    "showtime": "Tuesday, April 28, 12:00PM (Free)",
    "link": "https://tiff.net/events/setting-the-scene-exhibition-open-hours",
    "source": "TIFF Bell Lightbox"
  },
  {
    "title": "Film Reference Library Public Hours",
    "showtime": "Wednesday, April 29, 12:00PM (Free)",
    "link": "https://tiff.net/events/film-reference-library-public-hours",
    "source": "TIFF Bell Lightbox"
  },
  {
    "title": "Setting the Scene Exhibition",
    "showtime": "Wednesday, April 29, 12:00PM (Free)",
    "link": "https://tiff.net/events/setting-the-scene-exhibition-open-hours",
    "source": "TIFF Bell Lightbox"
  },
  {
    "title": "Film Reference Library Public Hours",
    "showtime": "Thursday, April 30, 12:00PM (Free)",
    "link": "https://tiff.net/events/film-reference-library-public-hours",
    "source": "TIFF Bell Lightbox"
  },
  {
    "title": "Setting the Scene Exhibition",
    "showtime": "Thursday, April 30, 12:00PM (Free)",
    "link": "https://tiff.net/events/setting-the-scene-exhibition-open-hours",
    "source": "TIFF Bell Lightbox"
  },
  {
    "title": "Film Reference Library Public Hours",
    "showtime": "Friday, May 1, 12:00PM (Free)",
    "link": "https://tiff.net/events/film-reference-library-public-hours",
    "source": "TIFF Bell Lightbox"
  },
  {
    "title": "Setting the Scene Exhibition",
    "showtime": "Friday, May 1, 12:00PM (Free)",
    "link": "https://tiff.net/events/setting-the-scene-exhibition-open-hours",
    "source": "TIFF Bell Lightbox"
  },
  {
    "title": "Film Reference Library Public Hours",
    "showtime": "Saturday, May 2, 12:00PM (Free)",
    "link": "https://tiff.net/events/film-reference-library-public-hours",
    "source": "TIFF Bell Lightbox"
  },
  {
    "title": "Setting the Scene Exhibition",
    "showtime": "Saturday, May 2, 12:00PM (Free)",
    "link": "https://tiff.net/events/setting-the-scene-exhibition-open-hours",
    "source": "TIFF Bell Lightbox"
  },
  {
    "title": "Film Reference Library Public Hours",
    "showtime": "Tuesday, May 5, 12:00PM (Free)",
    "link": "https://tiff.net/events/film-reference-library-public-hours",
    "source": "TIFF Bell Lightbox"
  },
  {
    "title": "Secret Movie Club",
    "showtime": "Tuesday, May 5, 7:00PM",
    "link": "https://am.ticketmaster.com/tiff/buy/ism/NlkwNTcwVDE=",
    "source": "TIFF Bell Lightbox"
  },
  {
    "title": "Setting the Scene Exhibition",
    "showtime": "Tuesday, May 5, 12:00PM (Free)",
    "link": "https://tiff.net/events/setting-the-scene-exhibition-open-hours",
    "source": "TIFF Bell Lightbox"
  },
  {
    "title": "Film Reference Library Public Hours",
    "showtime": "Wednesday, May 6, 12:00PM (Free)",
    "link": "https://tiff.net/events/film-reference-library-public-hours",
    "source": "TIFF Bell Lightbox"
  },
  {
    "title": "Setting the Scene Exhibition",
    "showtime": "Wednesday, May 6, 12:00PM (Free)",
    "link": "https://tiff.net/events/setting-the-scene-exhibition-open-hours",
    "source": "TIFF Bell Lightbox"
  },
  {
    "title": "Film Reference Library Public Hours",
    "showtime": "Thursday, May 7, 12:00PM (Free)",
    "link": "https://tiff.net/events/film-reference-library-public-hours",
    "source": "TIFF Bell Lightbox"
  },
  {
    "title": "Setting the Scene Exhibition",
    "showtime": "Thursday, May 7, 12:00PM (Free)",
    "link": "https://tiff.net/events/setting-the-scene-exhibition-open-hours",
    "source": "TIFF Bell Lightbox"
  },
  {
    "title": "Film Reference Library Public Hours",
    "showtime": "Friday, May 8, 12:00PM (Free)",
    "link": "https://tiff.net/events/film-reference-library-public-hours",
    "source": "TIFF Bell Lightbox"
  },
  {
    "title": "Setting the Scene Exhibition",
    "showtime": "Friday, May 8, 12:00PM (Free)",
    "link": "https://tiff.net/events/setting-the-scene-exhibition-open-hours",
    "source": "TIFF Bell Lightbox"
  },
  {
    "title": "Film Reference Library Public Hours",
    "showtime": "Saturday, May 9, 12:00PM (Free)",
    "link": "https://tiff.net/events/film-reference-library-public-hours",
    "source": "TIFF Bell Lightbox"
  },
  {
    "title": "Setting the Scene Exhibition",
    "showtime": "Saturday, May 9, 12:00PM (Free)",
    "link": "https://tiff.net/events/setting-the-scene-exhibition-open-hours",
    "source": "TIFF Bell Lightbox"
  },
  {
    "title": "Film Reference Library Public Hours",
    "showtime": "Tuesday, May 12, 12:00PM (Free)",
    "link": "https://tiff.net/events/film-reference-library-public-hours",
    "source": "TIFF Bell Lightbox"
  },
  {
    "title": "Setting the Scene Exhibition",
    "showtime": "Tuesday, May 12, 12:00PM (Free)",
    "link": "https://tiff.net/events/setting-the-scene-exhibition-open-hours",
    "source": "TIFF Bell Lightbox"
  },
  {
    "title": "Film Reference Library Public Hours",
    "showtime": "Wednesday, May 13, 12:00PM (Free)",
    "link": "https://tiff.net/events/film-reference-library-public-hours",
    "source": "TIFF Bell Lightbox"
  },
  {
    "title": "Setting the Scene Exhibition",
    "showtime": "Wednesday, May 13, 12:00PM (Free)",
    "link": "https://tiff.net/events/setting-the-scene-exhibition-open-hours",
    "source": "TIFF Bell Lightbox"
  },
  {
    "title": "Film Reference Library Public Hours",
    "showtime": "Thursday, May 14, 12:00PM (Free)",
    "link": "https://tiff.net/events/film-reference-library-public-hours",
    "source": "TIFF Bell Lightbox"
  },
  {
    "title": "Setting the Scene Exhibition",
    "showtime": "Thursday, May 14, 12:00PM (Free)",
    "link": "https://tiff.net/events/setting-the-scene-exhibition-open-hours",
    "source": "TIFF Bell Lightbox"
  },
  {
    "title": "Film Reference Library Public Hours",
    "showtime": "Friday, May 15, 12:00PM (Free)",
    "link": "https://tiff.net/events/film-reference-library-public-hours",
    "source": "TIFF Bell Lightbox"
  },
  {
    "title": "Setting the Scene Exhibition",
    "showtime": "Friday, May 15, 12:00PM (Free)",
    "link": "https://tiff.net/events/setting-the-scene-exhibition-open-hours",
    "source": "TIFF Bell Lightbox"
  },
  {
    "title": "Film Reference Library Public Hours",
    "showtime": "Saturday, May 16, 12:00PM (Free)",
    "link": "https://tiff.net/events/film-reference-library-public-hours",
    "source": "TIFF Bell Lightbox"
  },
  {
    "title": "Setting the Scene Exhibition",
    "showtime": "Saturday, May 16, 12:00PM (Free)",
    "link": "https://tiff.net/events/setting-the-scene-exhibition-open-hours",
    "source": "TIFF Bell Lightbox"
  },
  {
    "title": "Film Reference Library Public Hours",
    "showtime": "Tuesday, May 19, 12:00PM (Free)",
    "link": "https://tiff.net/events/film-reference-library-public-hours",
    "source": "TIFF Bell Lightbox"
  },
  {
    "title": "Setting the Scene Exhibition",
    "showtime": "Tuesday, May 19, 12:00PM (Free)",
    "link": "https://tiff.net/events/setting-the-scene-exhibition-open-hours",
    "source": "TIFF Bell Lightbox"
  },
  {
    "title": "Film Reference Library Public Hours",
    "showtime": "Wednesday, May 20, 12:00PM (Free)",
    "link": "https://tiff.net/events/film-reference-library-public-hours",
    "source": "TIFF Bell Lightbox"
  },
  {
    "title": "Setting the Scene Exhibition",
    "showtime": "Wednesday, May 20, 12:00PM (Free)",
    "link": "https://tiff.net/events/setting-the-scene-exhibition-open-hours",
    "source": "TIFF Bell Lightbox"
  },
  {
    "title": "Film Reference Library Public Hours",
    "showtime": "Thursday, May 21, 12:00PM (Free)",
    "link": "https://tiff.net/events/film-reference-library-public-hours",
    "source": "TIFF Bell Lightbox"
  },
  {
    "title": "Setting the Scene Exhibition",
    "showtime": "Thursday, May 21, 12:00PM (Free)",
    "link": "https://tiff.net/events/setting-the-scene-exhibition-open-hours",
    "source": "TIFF Bell Lightbox"
  },
  {
    "title": "Film Reference Library Public Hours",
    "showtime": "Friday, May 22, 12:00PM (Free)",
    "link": "https://tiff.net/events/film-reference-library-public-hours",
    "source": "TIFF Bell Lightbox"
  },
  {
    "title": "Setting the Scene Exhibition",
    "showtime": "Friday, May 22, 12:00PM (Free)",
    "link": "https://tiff.net/events/setting-the-scene-exhibition-open-hours",
    "source": "TIFF Bell Lightbox"
  },
  {
    "title": "Film Reference Library Public Hours",
    "showtime": "Saturday, May 23, 12:00PM (Free)",
    "link": "https://tiff.net/events/film-reference-library-public-hours",
    "source": "TIFF Bell Lightbox"
  },
  {
    "title": "Setting the Scene Exhibition",
    "showtime": "Saturday, May 23, 12:00PM (Free)",
    "link": "https://tiff.net/events/setting-the-scene-exhibition-open-hours",
    "source": "TIFF Bell Lightbox"
  },
  {
    "title": "Film Reference Library Public Hours",
    "showtime": "Tuesday, May 26, 12:00PM (Free)",
    "link": "https://tiff.net/events/film-reference-library-public-hours",
    "source": "TIFF Bell Lightbox"
  },
  {
    "title": "Setting the Scene Exhibition",
    "showtime": "Tuesday, May 26, 12:00PM (Free)",
    "link": "https://tiff.net/events/setting-the-scene-exhibition-open-hours",
    "source": "TIFF Bell Lightbox"
  },
  {
    "title": "Film Reference Library Public Hours",
    "showtime": "Wednesday, May 27, 12:00PM (Free)",
    "link": "https://tiff.net/events/film-reference-library-public-hours",
    "source": "TIFF Bell Lightbox"
  },
  {
    "title": "Setting the Scene Exhibition",
    "showtime": "Wednesday, May 27, 12:00PM (Free)",
    "link": "https://tiff.net/events/setting-the-scene-exhibition-open-hours",
    "source": "TIFF Bell Lightbox"
  }
]